[{"cn":"CyborgMonster Трейд","pi":"1529","ui":"7602259","ci":"2931","ri":"2939","ti":"422075","t":58,"r":58,"q":18.45,"p":4500.0,"mot":"U","mo":0},{"cn":"Alpiri Ltd.","pi":"1529","ui":"9462210","ci":"2931","ri":"2939","ti":"422075","t":49396,"r":49396,"q":1.0,"p":5999.0,"mot":"U","mo":0},{"cn":"Alpiri Ltd.","pi":"1529","ui":"9476553","ci":"2931","ri":"2945","ti":"424301","t":46819,"r":46819,"q":4.17,"p":5999.0,"mot":"U","mo":0},{"cn":"Alpiri Ltd.","pi":"1529","ui":"9481626","ci":"2931","ri":"2945","ti":"424305","t":24008,"r":24008,"q":8.1,"p":5999.0,"mot":"U","mo":0},{"cn":"Alpiri Ltd.","pi":"1529","ui":"9485781","ci":"2931","ri":"2945","ti":"424305","t":22158,"r":22158,"q":10.74,"p":5999.0,"mot":"U","mo":0},{"cn":"Alpiri Ltd.","pi":"1529","ui":"9460791","ci":"310392","ri":"310393","ti":"423019","t":25451,"r":25451,"q":1.03,"p":5999.0,"mot":"U","mo":0},{"cn":"1","pi":"1529","ui":"7686708","ci":"310392","ri":"310393","ti":"423567","t":1965867,"r":1965867,"q":37.54,"p":6000.0,"mot":"U","mo":0},{"cn":"rusco1\u0026Corp","pi":"1529","ui":"2237021","ci":"3010","ri":"3018","ti":"3022","t":19156,"r":8649,"q":32.02,"p":6490.0,"mot":"U","mo":0},{"cn":"Compania UDM","pi":"1529","ui":"8354388","ci":"310392","ri":"310393","ti":"424285","t":200,"r":200,"q":15.5,"p":6500.0,"mot":"U","mo":0},{"cn":"Delirium_T ink.","pi":"1529","ui":"7494320","ci":"2931","ri":"2950","ti":"422955","t":4026,"r":4026,"q":17.21,"p":6700.0,"mot":"U","mo":0},{"cn":"Alpiri Ltd.","pi":"1529","ui":"9498391","ci":"2931","ri":"2945","ti":"424304","t":9139,"r":9139,"q":14.78,"p":6999.0,"mot":"U","mo":0},{"cn":"Ksaveriy Финанс","pi":"1529","ui":"4269537","ci":"310392","ri":"310393","ti":"310400","t":514,"r":514,"q":26.32,"p":7800.0,"mot":"U","mo":0},{"cn":"ООО \"Максимус\"","pi":"1529","ui":"7545401","ci":"310392","ri":"310393","ti":"310400","t":1886540,"r":1885535,"q":33.51,"p":7990.0,"mot":"U","mo":0},{"cn":"СтройБизнес","pi":"1529","ui":"9310077","ci":"2931","ri":"2932","ti":"424287","t":259299,"r":259299,"q":24.48,"p":8000.0,"mot":"U","mo":0},{"cn":"СтройБизнес","pi":"1529","ui":"7358863","ci":"3010","ri":"3018","ti":"3020","t":49539,"r":49539,"q":30.98,"p":8000.0,"mot":"U","mo":0},{"cn":"BelKOZ inc.","pi":"1529","ui":"8760963","ci":"2931","ri":"2956","ti":"2957","t":787312,"r":787312,"q":28.71,"p":9000.0,"mot":"U","mo":0},{"cn":"Doltius","pi":"1529","ui":"9431380","ci":"2931","ri":"2956","ti":"424547","t":4567,"r":4567,"q":40.19,"p":9040.0,"mot":"U","mo":0},{"cn":"Doltius","pi":"1529","ui":"8377470","ci":"310392","ri":"310393","ti":"423508","t":1362,"r":1362,"q":40.68,"p":9040.0,"mot":"U","mo":0},{"cn":"Doltius","pi":"1529","ui":"9174501","ci":"2931","ri":"2932","ti":"422040","t":18710,"r":18710,"q":40.95,"p":9888.0,"mot":"U","mo":0},{"cn":"ООО \"Максимус\"","pi":"1529","ui":"8038994","ci":"310392","ri":"310393","ti":"310400","t":7167882,"r":7165377,"q":44.6,"p":9990.0,"mot":"U","mo":0},{"cn":"Helik Ltd.","pi":"1529","ui":"9106152","ci":"2931","ri":"2950","ti":"2955","t":15629,"r":15629,"q":23.56,"p":9999.0,"mot":"U","mo":0},{"cn":"Doltius","pi":"1529","ui":"7884880","ci":"3010","ri":"3011","ti":"422041","t":1308,"r":1308,"q":40.95,"p":9999.0,"mot":"U","mo":0},{"cn":"Sirvar","pi":"1529","ui":"9103249","ci":"3010","ri":"3018","ti":"3019","t":55718,"r":55718,"q":42.27,"p":9999.99,"mot":"U","mo":0},{"cn":"TVL Limited","pi":"1529","ui":"4676088","ci":"325645","ri":"325646","ti":"325649","t":8233,"r":8233,"q":13.71,"p":10000.0,"mot":"U","mo":0},{"cn":"VAM +","pi":"1529","ui":"9483225","ci":"3010","ri":"3011","ti":"424010","t":27705,"r":27705,"q":1.0,"p":11000.0,"mot":"L","mo":500},{"cn":"Крутицкий Финанс","pi":"1529","ui":"9038333","ci":"310392","ri":"310393","ti":"424285","t":130,"r":130,"q":44.73,"p":12300.0,"mot":"U","mo":0},{"cn":"Пушкин А. Ltd.","pi":"1529","ui":"9405096","ci":"325645","ri":"325646","ti":"325648","t":35154,"r":35154,"q":18.97,"p":15000.0,"mot":"U","mo":0},{"cn":"RZN Ltd.","pi":"1529","ui":"8865772","ci":"325650","ri":"325651","ti":"325654","t":112823,"r":7823,"q":50.49,"p":15000.0,"mot":"U","mo":0},{"cn":"Doltius","pi":"1529","ui":"3759046","ci":"2931","ri":"2932","ti":"2933","t":287,"r":287,"q":45.07,"p":17000.0,"mot":"U","mo":0},{"cn":"Dimsan Invest","pi":"1529","ui":"8701452","ci":"2931","ri":"2956","ti":"424279","t":60,"r":60,"q":24.81,"p":17500.0,"mot":"U","mo":0},{"cn":"Sergey_Ger Финанс","pi":"1529","ui":"8637809","ci":"422187","ri":"422188","ti":"422192","t":743225,"r":743225,"q":44.78,"p":18000.0,"mot":"U","mo":0},{"cn":"PS_loki Трейд","pi":"1529","ui":"8904501","ci":"310392","ri":"310393","ti":"310400","t":209590,"r":209590,"q":40.74,"p":19999.99,"mot":"U","mo":0},{"cn":"Время","pi":"1529","ui":"6086118","ci":"310392","ri":"310393","ti":"310400","t":2933,"r":2933,"q":30.02,"p":20000.0,"mot":"U","mo":0},{"cn":"PS_loki Трейд","pi":"1529","ui":"8216380","ci":"310392","ri":"310393","ti":"310400","t":3190382,"r":3190382,"q":42.17,"p":23900.0,"mot":"U","mo":0},{"cn":"TVL Limited","pi":"1529","ui":"6852011","ci":"423195","ri":"423196","ti":"423207","t":22345,"r":22345,"q":22.06,"p":25000.0,"mot":"U","mo":0},{"cn":"ООО Ремстрой","pi":"1529","ui":"6286390","ci":"310392","ri":"310393","ti":"310400","t":64051646,"r":64051646,"q":43.41,"p":29900.0,"mot":"U","mo":0},{"cn":"aleksandr260 Инвест","pi":"1529","ui":"3206346","ci":"2931","ri":"2961","ti":"2962","t":324068,"r":324068,"q":27.7,"p":32000.0,"mot":"U","mo":0},{"cn":"ООО \"Максимус\"","pi":"1529","ui":"7348639","ci":"310392","ri":"310393","ti":"310400","t":7232041,"r":7232041,"q":47.64,"p":36990.0,"mot":"U","mo":0},{"cn":"Acme Corporation inc.","pi":"1529","ui":"7925338","ci":"310392","ri":"310393","ti":"310400","t":11870751,"r":11870751,"q":1.0,"p":40000.0,"mot":"U","mo":0},{"cn":"ООО \"Максимус\"","pi":"1529","ui":"7835273","ci":"310392","ri":"310393","ti":"310400","t":1938646,"r":1938646,"q":48.37,"p":41990.0,"mot":"U","mo":0},{"cn":"ООО \"Максимус\"","pi":"1529","ui":"8188112","ci":"310392","ri":"310393","ti":"310400","t":6079351,"r":6079351,"q":49.08,"p":49990.0,"mot":"U","mo":0},{"cn":"TVL Limited","pi":"1529","ui":"3288822","ci":"15734","ri":"15735","ti":"15741","t":562908,"r":562908,"q":27.28,"p":50000.0,"mot":"U","mo":0},{"cn":"TVL Limited","pi":"1529","ui":"3448938","ci":"15734","ri":"15735","ti":"15741","t":16727,"r":16727,"q":42.22,"p":50000.0,"mot":"U","mo":0},{"cn":"АО \"МММ\"","pi":"1529","ui":"8188383","ci":"2931","ri":"2932","ti":"422040","t":413550,"r":413550,"q":33.43,"p":50000.0,"mot":"U","mo":0},{"cn":"radium\u0026kobedin","pi":"1529","ui":"3080915","ci":"2931","ri":"2932","ti":"2936","t":5231,"r":231,"q":68.9,"p":63000.0,"mot":"U","mo":0},{"cn":"TVL Limited","pi":"1529","ui":"6009211","ci":"3054","ri":"3055","ti":"3057","t":1193615,"r":1193615,"q":37.17,"p":80000.0,"mot":"U","mo":0},{"cn":"ZAO Pchelka","pi":"1529","ui":"5833127","ci":"310392","ri":"310393","ti":"310400","t":542286,"r":542286,"q":52.45,"p":100000.0,"mot":"U","mo":0},{"cn":"ООО \"Максимус\"","pi":"1529","ui":"7359872","ci":"310392","ri":"310393","ti":"310400","t":578845,"r":578845,"q":56.75,"p":139990.0,"mot":"U","mo":0},{"cn":"Молот Финанс","pi":"1529","ui":"8611270","ci":"422187","ri":"422188","ti":"422189","t":132094856,"r":132074856,"q":57.49,"p":150000.0,"mot":"U","mo":0},{"cn":"TVL Limited","pi":"1529","ui":"3859955","ci":"3010","ri":"3023","ti":"3028","t":94929,"r":94929,"q":40.78,"p":220000.0,"mot":"L","mo":5000},{"cn":"АО «Monkk»","pi":"1529","ui":"8242600","ci":"310392","ri":"310393","ti":"310400","t":610943,"r":610943,"q":62.46,"p":599990.0,"mot":"U","mo":0},{"cn":"ООО \"Максимус\"","pi":"1529","ui":"7144971","ci":"310392","ri":"310393","ti":"310400","t":1809673,"r":1809673,"q":56.42,"p":9999990.0,"mot":"U","mo":0},{"cn":"xxx123456789xxx Инвест","pi":"1529","ui":"7202251","ci":"424181","ri":"424184","ti":"424195","t":309,"r":309,"q":7.0,"p":5.0E7,"mot":"U","mo":0},{"cn":"Mocca Ltd.","pi":"1529","ui":"7836628","ci":"424181","ri":"424182","ti":"424187","t":301,"r":301,"q":7.0,"p":5.0E10,"mot":"U","mo":0},{"cn":"Seryoga4888","pi":"1529","ui":"6913481","ci":"310392","ri":"310393","ti":"310400","t":15769,"r":15769,"q":56.54,"p":9.9999999999E10,"mot":"L","mo":999}]