[{"ci":"422653","ri":"422657","ti":"422671","tc":"Индианаполис","wi":43.84,"ei":6.0,"as":749.98,"pi":"373201","pci":"1531","mi":"E","v":577189,"sc":2,"cc":2,"lpe":98.79,"lpr":185.34,"lq":1.0,"spr":186.141505226191,"sq":1.11,"sb":0.02,"itr":33.0,"itp":0,"lmvs":1.06976209E8,"smvs":1757032.0,"lmvst":1.06976209E8,"smvst":1757032.0,"pmvs":1.64,"pmvst":1.64},{"ci":"422653","ri":"422656","ti":"422672","tc":"Джексонвиль","wi":47.76,"ei":7.0,"as":1078.25,"pi":"373201","pci":"1531","mi":"E","v":612809,"sc":4,"cc":3,"lpe":93.15,"lpr":225.55,"lq":1.0,"spr":241.96114931406,"sq":2.01,"sb":0.2,"itr":20.0,"itp":0,"lmvs":1.3821907E8,"smvs":1.9524906E7,"lmvst":1.3821907E8,"smvst":1.9524906E7,"pmvs":14.13,"pmvst":14.13},{"ci":"422653","ri":"422657","ti":"422674","tc":"Колумбус","wi":45.57,"ei":7.0,"as":796.1,"pi":"373201","pci":"1531","mi":"E","v":532069,"sc":2,"cc":2,"lpe":98.87,"lpr":179.07,"lq":1.0,"spr":180.076598768205,"sq":1.11,"sb":0.02,"itr":33.0,"itp":0,"lmvs":9.5277596E7,"smvs":1612217.0,"lmvst":9.5277596E7,"smvst":1612217.0,"pmvs":1.69,"pmvst":1.69},{"ci":"2931","ri":"2939","ti":"2944","tc":"Пермь","wi":9.31,"ei":5.89,"as":288.61,"pi":"373201","pci":"1531","mi":"E","v":674279,"sc":1,"cc":1,"lpe":99.84,"lpr":54.94,"lq":1.0,"spr":54.9278625910046,"sq":1.0,"sb":0.0,"itr":21.0,"itp":1,"lmvs":3.7044888E7,"smvs":51088.0,"lmvst":3.7044888E7,"smvst":51088.0,"pmvs":0.14,"pmvst":0.14},{"ci":"422653","ri":"422659","ti":"422669","tc":"Сан-Хосе","wi":49.39,"ei":7.0,"as":1230.33,"pi":"373201","pci":"1531","mi":"E","v":568346,"sc":3,"cc":3,"lpe":97.7,"lpr":162.15,"lq":1.28,"spr":165.536271566968,"sq":1.51,"sb":0.02,"itr":39.0,"itp":0,"lmvs":9.2157304E7,"smvs":4044192.0,"lmvst":9.2157304E7,"smvst":4044192.0,"pmvs":4.39,"pmvst":4.39},{"ci":"2931","ri":"2939","ti":"2943","tc":"Казань","wi":20.66,"ei":13.7,"as":469.4,"pi":"373201","pci":"1531","mi":"E","v":2196081,"sc":2,"cc":2,"lpe":99.93,"lpr":78.6,"lq":1.0,"spr":78.6015026768138,"sq":1.0,"sb":0.0,"itr":21.0,"itp":1,"lmvs":1.72611967E8,"smvs":124128.0,"lmvst":1.72611967E8,"smvst":124128.0,"pmvs":0.07,"pmvst":0.07},{"ci":"2931","ri":"2939","ti":"2942","tc":"Уфа","wi":16.85,"ei":16.14,"as":300.08,"pi":"373201","pci":"1531","mi":"E","v":1481408,"sc":1,"cc":1,"lpe":99.85,"lpr":78.3,"lq":1.0,"spr":78.2965067017324,"sq":1.0,"sb":0.0,"itr":21.0,"itp":1,"lmvs":1.15994246E8,"smvs":168816.0,"lmvst":1.15994246E8,"smvst":168816.0,"pmvs":0.15,"pmvst":0.15},{"ci":"2931","ri":"2939","ti":"2941","tc":"Самара","wi":8.92,"ei":8.93,"as":271.6,"pi":"373201","pci":"1531","mi":"?","v":1578857,"sc":0,"cc":0,"lpe":100.0,"lpr":26.99,"lq":1.0,"spr":26.99,"sq":1.0,"sb":0.0,"itr":21.0,"itp":1,"lmvs":4.261335E7,"smvs":0.0,"lmvst":4.261335E7,"smvst":0.0,"pmvs":0.0,"pmvst":0.0},{"ci":"17597","ri":"17598","ti":"17608","tc":"Бильбао","wi":22.5,"ei":5.0,"as":260.0,"pi":"373201","pci":"1531","mi":"E","v":485651,"sc":1,"cc":1,"lpe":99.79,"lpr":143.98,"lq":1.0,"spr":143.971804814568,"sq":1.03,"sb":0.0,"itr":20.0,"itp":0,"lmvs":6.9924031E7,"smvs":142860.0,"lmvst":6.9924031E7,"smvst":142860.0,"pmvs":0.2,"pmvst":0.2},{"ci":"424181","ri":"424184","ti":"424204","tc":"Шеллефтео","wi":24.98,"ei":5.9,"as":431.2,"pi":"373201","pci":"1531","mi":"?","v":51565,"sc":0,"cc":0,"lpe":100.0,"lpr":112.99,"lq":1.0,"spr":112.99,"sq":1.0,"sb":0.0,"itr":15.0,"itp":0,"lmvs":5826329.0,"smvs":0.0,"lmvst":5826329.0,"smvst":0.0,"pmvs":0.0,"pmvst":0.0},{"ci":"422653","ri":"422655","ti":"422664","tc":"Филадельфия","wi":54.41,"ei":7.0,"as":1000.0,"pi":"373201","pci":"1531","mi":"E","v":1086007,"sc":5,"cc":5,"lpe":95.53,"lpr":275.67,"lq":1.0,"spr":277.808066329223,"sq":1.19,"sb":0.01,"itr":24.0,"itp":0,"lmvs":2.9937955E8,"smvs":1.5704221E7,"lmvst":2.9937955E8,"smvst":1.5704221E7,"pmvs":5.25,"pmvst":5.25},{"ci":"2931","ri":"2939","ti":"2940","tc":"Нижний Новгород","wi":30.96,"ei":13.87,"as":473.48,"pi":"373201","pci":"1531","mi":"E","v":2384103,"sc":1,"cc":1,"lpe":99.95,"lpr":161.53,"lq":1.0,"spr":161.527100586678,"sq":1.0,"sb":0.0,"itr":21.0,"itp":1,"lmvs":3.85104158E8,"smvs":185640.0,"lmvst":3.85104158E8,"smvst":185640.0,"pmvs":0.05,"pmvst":0.05},{"ci":"422653","ri":"422658","ti":"422665","tc":"Финикс","wi":55.87,"ei":7.0,"as":994.0,"pi":"373201","pci":"1531","mi":"E","v":1008630,"sc":5,"cc":5,"lpe":97.43,"lpr":282.23,"lq":1.0,"spr":283.468802345756,"sq":1.16,"sb":0.02,"itr":31.0,"itp":0,"lmvs":2.84665645E8,"smvs":8565400.0,"lmvst":2.84665645E8,"smvst":8565400.0,"pmvs":3.01,"pmvst":3.01},{"ci":"422653","ri":"422658","ti":"422666","tc":"Сан-Антонио","wi":56.61,"ei":7.0,"as":1036.07,"pi":"373201","pci":"1531","mi":"E","v":927973,"sc":6,"cc":6,"lpe":95.92,"lpr":277.76,"lq":1.0,"spr":279.963624976158,"sq":1.34,"sb":0.04,"itr":31.0,"itp":0,"lmvs":2.5775378E8,"smvs":1.2561259E7,"lmvst":2.5775378E8,"smvst":1.2561259E7,"pmvs":4.87,"pmvst":4.87},{"ci":"422653","ri":"422659","ti":"422667","tc":"Сан-Диего","wi":44.14,"ei":7.76,"as":812.25,"pi":"373201","pci":"1531","mi":"E","v":621087,"sc":2,"cc":2,"lpe":99.83,"lpr":174.52,"lq":1.0,"spr":174.558925045928,"sq":1.02,"sb":0.0,"itr":39.0,"itp":0,"lmvs":1.08392103E8,"smvs":208442.0,"lmvst":1.08392103E8,"smvst":208442.0,"pmvs":0.19,"pmvst":0.19},{"ci":"17597","ri":"17598","ti":"17604","tc":"Малага","wi":32.34,"ei":7.0,"as":266.4,"pi":"373201","pci":"1531","mi":"E","v":319598,"sc":1,"cc":1,"lpe":99.69,"lpr":168.24,"lq":1.0,"spr":168.433242761219,"sq":1.04,"sb":0.0,"itr":20.0,"itp":0,"lmvs":5.3769168E7,"smvs":228444.0,"lmvst":5.3769168E7,"smvst":228444.0,"pmvs":0.42,"pmvst":0.42},{"ci":"17597","ri":"17598","ti":"17605","tc":"Мурсия","wi":26.64,"ei":7.76,"as":406.0,"pi":"373201","pci":"1531","mi":"E","v":564146,"sc":3,"cc":3,"lpe":93.53,"lpr":133.02,"lq":1.0,"spr":134.06642741418,"sq":1.25,"sb":0.0,"itr":20.0,"itp":0,"lmvs":7.5042701E7,"smvs":5445601.0,"lmvst":7.5042701E7,"smvst":5445601.0,"pmvs":7.26,"pmvst":7.26},{"ci":"17597","ri":"17598","ti":"17606","tc":"Лас-Пальмас-де-Гран-Канария","wi":45.64,"ei":5.0,"as":287.0,"pi":"373201","pci":"1531","mi":"E","v":257361,"sc":3,"cc":3,"lpe":89.51,"lpr":221.85,"lq":1.49,"spr":226.901464674135,"sq":1.88,"sb":0.01,"itr":20.0,"itp":0,"lmvs":5.7095538E7,"smvs":7289372.0,"lmvst":5.7095538E7,"smvst":7289372.0,"pmvs":12.77,"pmvst":12.77},{"ci":"17597","ri":"17598","ti":"17607","tc":"Пальма-де-Майорка","wi":46.02,"ei":4.0,"as":281.0,"pi":"373201","pci":"1531","mi":"E","v":247843,"sc":1,"cc":1,"lpe":99.6,"lpr":268.36,"lq":1.0,"spr":268.689402081156,"sq":1.05,"sb":0.01,"itr":20.0,"itp":0,"lmvs":6.6511147E7,"smvs":347685.0,"lmvst":6.6511147E7,"smvst":347685.0,"pmvs":0.52,"pmvst":0.52},{"ci":"2931","ri":"2945","ti":"2949","tc":"Новороссийск","wi":9.9,"ei":9.21,"as":392.73,"pi":"373201","pci":"1531","mi":"?","v":97849,"sc":0,"cc":0,"lpe":100.0,"lpr":135.23,"lq":1.0,"spr":135.23,"sq":1.0,"sb":0.0,"itr":30.0,"itp":1,"lmvs":1.323212E7,"smvs":0.0,"lmvst":1.323212E7,"smvst":0.0,"pmvs":0.0,"pmvst":0.0},{"ci":"17597","ri":"17598","ti":"17600","tc":"Барселона","wi":32.64,"ei":7.0,"as":262.0,"pi":"373201","pci":"1531","mi":"E","v":1196489,"sc":2,"cc":2,"lpe":97.41,"lpr":170.09,"lq":1.0,"spr":170.396906289987,"sq":1.1,"sb":0.0,"itr":20.0,"itp":0,"lmvs":2.03510814E8,"smvs":5638140.0,"lmvst":2.03510814E8,"smvst":5638140.0,"pmvs":2.77,"pmvst":2.77},{"ci":"2931","ri":"2945","ti":"2948","tc":"Краснодар","wi":8.02,"ei":5.0,"as":150.0,"pi":"373201","pci":"1531","mi":"?","v":3301406,"sc":0,"cc":0,"lpe":100.0,"lpr":57.21,"lq":1.0,"spr":57.21,"sq":1.0,"sb":0.0,"itr":30.0,"itp":1,"lmvs":1.88873437E8,"smvs":0.0,"lmvst":1.88873437E8,"smvst":0.0,"pmvs":0.0,"pmvst":0.0},{"ci":"17597","ri":"17598","ti":"17601","tc":"Валенсия","wi":32.1,"ei":6.0,"as":255.0,"pi":"373201","pci":"1531","mi":"E","v":566118,"sc":3,"cc":3,"lpe":94.54,"lpr":168.07,"lq":1.0,"spr":170.275138169074,"sq":1.26,"sb":0.0,"itr":20.0,"itp":0,"lmvs":9.5147452E7,"smvs":6443419.0,"lmvst":9.5147452E7,"smvst":6443419.0,"pmvs":6.77,"pmvst":6.77},{"ci":"2931","ri":"2945","ti":"2947","tc":"Волгоград","wi":24.92,"ei":5.99,"as":322.5,"pi":"373201","pci":"1531","mi":"?","v":364843,"sc":0,"cc":0,"lpe":100.0,"lpr":113.72,"lq":1.0,"spr":113.72,"sq":1.0,"sb":0.0,"itr":30.0,"itp":1,"lmvs":4.1489946E7,"smvs":0.0,"lmvst":4.1489946E7,"smvst":0.0,"pmvs":0.0,"pmvst":0.0},{"ci":"17597","ri":"17598","ti":"17602","tc":"Севилья","wi":32.33,"ei":6.0,"as":270.0,"pi":"373201","pci":"1531","mi":"E","v":650820,"sc":1,"cc":1,"lpe":99.85,"lpr":170.28,"lq":1.0,"spr":170.371761162841,"sq":1.02,"sb":0.0,"itr":20.0,"itp":0,"lmvs":1.1082163E8,"smvs":225952.0,"lmvst":1.1082163E8,"smvst":225952.0,"pmvs":0.2,"pmvst":0.2},{"ci":"2931","ri":"2945","ti":"2946","tc":"Ростов-на-Дону","wi":19.12,"ei":7.71,"as":373.7,"pi":"373201","pci":"1531","mi":"?","v":577034,"sc":0,"cc":0,"lpe":100.0,"lpr":134.76,"lq":1.0,"spr":134.76,"sq":1.0,"sb":0.0,"itr":30.0,"itp":1,"lmvs":7.7761102E7,"smvs":0.0,"lmvst":7.7761102E7,"smvst":0.0,"pmvs":0.0,"pmvst":0.0},{"ci":"17597","ri":"17598","ti":"17603","tc":"Сарагоса","wi":35.7,"ei":7.54,"as":409.0,"pi":"373201","pci":"1531","mi":"E","v":746682,"sc":3,"cc":3,"lpe":99.65,"lpr":168.78,"lq":1.0,"spr":168.89100947927,"sq":1.03,"sb":0.0,"itr":20.0,"itp":0,"lmvs":1.26024988E8,"smvs":523976.0,"lmvst":1.26024988E8,"smvst":523976.0,"pmvs":0.42,"pmvst":0.42},{"ci":"15734","ri":"15735","ti":"302148","tc":"Молодечно","wi":10.44,"ei":4.68,"as":324.4,"pi":"373201","pci":"1531","mi":"E","v":16546,"sc":1,"cc":1,"lpe":93.96,"lpr":77.14,"lq":1.0,"spr":80.3347298440711,"sq":1.78,"sb":0.05,"itr":30.0,"itp":5,"lmvs":1276358.0,"smvs":129952.0,"lmvst":1276358.0,"smvst":129952.0,"pmvs":10.18,"pmvst":10.18},{"ci":"2931","ri":"2945","ti":"5033","tc":"Сочи","wi":31.97,"ei":7.75,"as":352.1,"pi":"373201","pci":"1531","mi":"E","v":444562,"sc":1,"cc":1,"lpe":99.98,"lpr":161.87,"lq":1.0,"spr":161.869335053378,"sq":1.0,"sb":0.0,"itr":30.0,"itp":1,"lmvs":7.1961251E7,"smvs":14097.0,"lmvst":7.1961251E7,"smvst":14097.0,"pmvs":0.02,"pmvst":0.02},{"ci":"424181","ri":"424182","ti":"424189","tc":"Линчепинг","wi":36.32,"ei":6.6,"as":519.4,"pi":"373201","pci":"1531","mi":"E","v":114156,"sc":2,"cc":2,"lpe":99.12,"lpr":176.59,"lq":1.0,"spr":176.61578813203,"sq":1.11,"sb":0.02,"itr":15.0,"itp":0,"lmvs":2.0158808E7,"smvs":180341.0,"lmvst":2.0158808E7,"smvst":180341.0,"pmvs":0.89,"pmvst":0.89},{"ci":"422653","ri":"422655","ti":"422682","tc":"Вашингтон","wi":46.15,"ei":7.0,"as":995.0,"pi":"373201","pci":"1531","mi":"E","v":446214,"sc":4,"cc":4,"lpe":91.37,"lpr":201.15,"lq":1.0,"spr":204.697457049756,"sq":1.31,"sb":0.01,"itr":24.0,"itp":0,"lmvs":8.9755946E7,"smvs":9328863.0,"lmvst":8.9755946E7,"smvst":9328863.0,"pmvs":10.39,"pmvst":10.39},{"ci":"422653","ri":"422654","ti":"422683","tc":"Бостон","wi":61.17,"ei":7.54,"as":1230.25,"pi":"373201","pci":"1531","mi":"E","v":279294,"sc":4,"cc":4,"lpe":83.85,"lpr":293.45,"lq":2.9,"spr":286.999467586128,"sq":3.81,"sb":0.18,"itr":33.0,"itp":0,"lmvs":8.1958824E7,"smvs":1.1434755E7,"lmvst":8.1958824E7,"smvst":1.1434755E7,"pmvs":13.95,"pmvst":13.95},{"ci":"422653","ri":"422654","ti":"422685","tc":"Хартфорд","wi":39.43,"ei":7.0,"as":1040.0,"pi":"373201","pci":"1531","mi":"E","v":86972,"sc":2,"cc":2,"lpe":95.4,"lpr":114.89,"lq":1.0,"spr":118.965334590443,"sq":1.45,"sb":0.14,"itr":33.0,"itp":0,"lmvs":9992213.0,"smvs":814082.0,"lmvst":9992213.0,"smvst":814082.0,"pmvs":8.15,"pmvst":8.15},{"ci":"424181","ri":"424183","ti":"424185","tc":"Стокгольм","wi":46.65,"ei":6.8,"as":509.6,"pi":"373201","pci":"1531","mi":"E","v":689236,"sc":7,"cc":6,"lpe":99.2,"lpr":219.75,"lq":1.0,"spr":219.640238249308,"sq":1.02,"sb":0.0,"itr":15.0,"itp":0,"lmvs":1.51459611E8,"smvs":1136025.0,"lmvst":1.51459611E8,"smvst":1136025.0,"pmvs":0.75,"pmvst":0.75},{"ci":"424181","ri":"424182","ti":"424186","tc":"Гетеборг","wi":47.7,"ei":6.9,"as":499.8,"pi":"373201","pci":"1531","mi":"E","v":407646,"sc":8,"cc":7,"lpe":93.95,"lpr":192.84,"lq":1.0,"spr":191.91920676273,"sq":1.2,"sb":0.01,"itr":15.0,"itp":0,"lmvs":7.8610455E7,"smvs":4380575.0,"lmvst":7.8610455E7,"smvst":4380575.0,"pmvs":5.57,"pmvst":5.57},{"ci":"424181","ri":"424182","ti":"424187","tc":"Мальме","wi":33.68,"ei":6.7,"as":470.4,"pi":"373201","pci":"1531","mi":"E","v":229288,"sc":4,"cc":4,"lpe":90.78,"lpr":165.92,"lq":1.0,"spr":158.792238233139,"sq":1.62,"sb":0.01,"itr":15.0,"itp":0,"lmvs":3.8043465E7,"smvs":1873297.0,"lmvst":3.8043465E7,"smvst":1873297.0,"pmvs":4.92,"pmvst":4.92},{"ci":"424181","ri":"424183","ti":"424188","tc":"Уппсала","wi":35.0,"ei":6.8,"as":480.2,"pi":"373201","pci":"1531","mi":"E","v":154281,"sc":1,"cc":1,"lpe":99.93,"lpr":175.99,"lq":1.0,"spr":175.968811972958,"sq":1.0,"sb":0.0,"itr":15.0,"itp":0,"lmvs":2.7151913E7,"smvs":15737.0,"lmvst":2.7151913E7,"smvst":15737.0,"pmvs":0.06,"pmvst":0.06},{"ci":"422653","ri":"422656","ti":"422679","tc":"Мемфис","wi":42.55,"ei":6.0,"as":928.15,"pi":"373201","pci":"1531","mi":"E","v":475281,"sc":2,"cc":2,"lpe":98.53,"lpr":139.78,"lq":1.0,"spr":140.443901986404,"sq":1.14,"sb":0.04,"itr":20.0,"itp":0,"lmvs":6.6434778E7,"smvs":1292131.0,"lmvst":6.6434778E7,"smvst":1292131.0,"pmvs":1.94,"pmvst":1.94},{"ci":"2931","ri":"2950","ti":"2955","tc":"Сургут","wi":10.1,"ei":5.8,"as":303.72,"pi":"373201","pci":"1531","mi":"E","v":58913,"sc":1,"cc":1,"lpe":99.83,"lpr":86.32,"lq":1.0,"spr":86.283811043403,"sq":1.02,"sb":0.0,"itr":20.0,"itp":1,"lmvs":5085370.0,"smvs":6513.0,"lmvst":5085370.0,"smvst":6513.0,"pmvs":0.13,"pmvst":0.13},{"ci":"2931","ri":"2950","ti":"2954","tc":"Магнитогорск","wi":7.9,"ei":13.97,"as":214.3,"pi":"373201","pci":"1531","mi":"E","v":139045,"sc":1,"cc":1,"lpe":99.82,"lpr":84.25,"lq":1.0,"spr":84.2153889028732,"sq":1.02,"sb":0.0,"itr":20.0,"itp":1,"lmvs":1.1714541E7,"smvs":16274.0,"lmvst":1.1714541E7,"smvst":16274.0,"pmvs":0.14,"pmvst":0.14},{"ci":"15906","ri":"15922","ti":"15959","tc":"Сент-Этьен","wi":33.56,"ei":5.0,"as":385.0,"pi":"373201","pci":"1531","mi":"E","v":145463,"sc":3,"cc":3,"lpe":97.83,"lpr":168.86,"lq":1.0,"spr":169.658766696686,"sq":1.21,"sb":0.04,"itr":17.0,"itp":13,"lmvs":2.4562882E7,"smvs":649206.0,"lmvst":2.4562882E7,"smvst":649206.0,"pmvs":2.64,"pmvst":2.64},{"ci":"2931","ri":"2950","ti":"2953","tc":"Тюмень","wi":8.51,"ei":7.44,"as":172.0,"pi":"373201","pci":"1531","mi":"E","v":153228,"sc":1,"cc":1,"lpe":99.93,"lpr":66.87,"lq":1.0,"spr":66.8492009293341,"sq":1.01,"sb":0.0,"itr":20.0,"itp":1,"lmvs":1.0246356E7,"smvs":3985.0,"lmvst":1.0246356E7,"smvst":3985.0,"pmvs":0.04,"pmvst":0.04},{"ci":"15906","ri":"15922","ti":"15958","tc":"Монпелье","wi":36.09,"ei":5.0,"as":498.0,"pi":"373201","pci":"1531","mi":"E","v":152736,"sc":4,"cc":3,"lpe":97.79,"lpr":171.81,"lq":1.0,"spr":172.152678216007,"sq":1.2,"sb":0.04,"itr":17.0,"itp":13,"lmvs":2.6241572E7,"smvs":632278.0,"lmvst":2.6241572E7,"smvst":632278.0,"pmvs":2.41,"pmvst":2.41},{"ci":"2931","ri":"2950","ti":"2952","tc":"Челябинск","wi":9.95,"ei":6.11,"as":298.4,"pi":"373201","pci":"1531","mi":"E","v":236911,"sc":1,"cc":1,"lpe":99.89,"lpr":89.17,"lq":1.0,"spr":89.149770884425,"sq":1.01,"sb":0.0,"itr":20.0,"itp":1,"lmvs":2.1125354E7,"smvs":18445.0,"lmvst":2.1125354E7,"smvst":18445.0,"pmvs":0.09,"pmvst":0.09},{"ci":"422653","ri":"422656","ti":"422675","tc":"Шарлотт","wi":48.91,"ei":7.0,"as":913.33,"pi":"373201","pci":"1531","mi":"E","v":576663,"sc":2,"cc":2,"lpe":96.36,"lpr":207.28,"lq":1.0,"spr":210.014907562996,"sq":1.33,"sb":0.09,"itr":20.0,"itp":0,"lmvs":1.19530707E8,"smvs":5928038.0,"lmvst":1.19530707E8,"smvst":5928038.0,"pmvs":4.96,"pmvst":4.96},{"ci":"2931","ri":"2950","ti":"2951","tc":"Екатеринбург","wi":21.17,"ei":13.76,"as":546.2,"pi":"373201","pci":"1531","mi":"E","v":2066141,"sc":1,"cc":1,"lpe":99.98,"lpr":79.77,"lq":1.0,"spr":79.7627957482089,"sq":1.0,"sb":0.0,"itr":20.0,"itp":1,"lmvs":1.64816068E8,"smvs":18078.0,"lmvst":1.64816068E8,"smvst":18078.0,"pmvs":0.01,"pmvst":0.01},{"ci":"15905","ri":"15921","ti":"15957","tc":"Дрезден","wi":33.14,"ei":7.0,"as":313.64,"pi":"373201","pci":"1531","mi":"E","v":363285,"sc":1,"cc":1,"lpe":99.72,"lpr":172.83,"lq":1.0,"spr":173.097475948635,"sq":1.04,"sb":0.0,"itr":22.0,"itp":32,"lmvs":6.2786547E7,"smvs":272972.0,"lmvst":6.2786547E7,"smvst":272972.0,"pmvs":0.43,"pmvst":0.43},{"ci":"2931","ri":"2956","ti":"2959","tc":"Красноярск","wi":19.92,"ei":8.56,"as":358.53,"pi":"373201","pci":"1531","mi":"?","v":1327164,"sc":0,"cc":0,"lpe":100.0,"lpr":82.4,"lq":1.0,"spr":82.4,"sq":1.0,"sb":0.0,"itr":30.0,"itp":1,"lmvs":1.09358314E8,"smvs":0.0,"lmvst":1.09358314E8,"smvst":0.0,"pmvs":0.0,"pmvst":0.0},{"ci":"15905","ri":"15921","ti":"15956","tc":"Лейпциг","wi":34.32,"ei":7.0,"as":315.0,"pi":"373201","pci":"1531","mi":"E","v":351624,"sc":1,"cc":1,"lpe":99.72,"lpr":173.74,"lq":1.0,"spr":174.013758332765,"sq":1.04,"sb":0.0,"itr":22.0,"itp":32,"lmvs":6.1091154E7,"smvs":267315.0,"lmvst":6.1091154E7,"smvst":267315.0,"pmvs":0.44,"pmvst":0.44},{"ci":"2931","ri":"2956","ti":"2958","tc":"Омск","wi":16.57,"ei":5.17,"as":280.0,"pi":"373201","pci":"1531","mi":"?","v":1320710,"sc":0,"cc":0,"lpe":100.0,"lpr":80.79,"lq":1.0,"spr":80.79,"sq":1.0,"sb":0.0,"itr":30.0,"itp":1,"lmvs":1.06700161E8,"smvs":0.0,"lmvst":1.06700161E8,"smvst":0.0,"pmvs":0.0,"pmvst":0.0},{"ci":"15905","ri":"15920","ti":"15955","tc":"Бонн","wi":60.1,"ei":6.0,"as":396.0,"pi":"373201","pci":"1531","mi":"E","v":192239,"sc":4,"cc":4,"lpe":85.33,"lpr":267.81,"lq":2.76,"spr":282.245220376719,"sq":3.12,"sb":0.01,"itr":22.0,"itp":32,"lmvs":5.1483527E7,"smvs":1.0327646E7,"lmvst":5.1483527E7,"smvst":1.0327646E7,"pmvs":20.06,"pmvst":20.06},{"ci":"2931","ri":"2956","ti":"2957","tc":"Новосибирск","wi":25.92,"ei":9.22,"as":360.5,"pi":"373201","pci":"1531","mi":"?","v":2181899,"sc":0,"cc":0,"lpe":100.0,"lpr":161.86,"lq":1.0,"spr":161.86,"sq":1.0,"sb":0.0,"itr":30.0,"itp":1,"lmvs":3.53162172E8,"smvs":0.0,"lmvst":3.53162172E8,"smvst":0.0,"pmvs":0.0,"pmvst":0.0},{"ci":"15905","ri":"15920","ti":"15954","tc":"Нюрнберг","wi":49.22,"ei":5.0,"as":337.0,"pi":"373201","pci":"1531","mi":"E","v":328174,"sc":2,"cc":2,"lpe":99.66,"lpr":266.45,"lq":1.0,"spr":266.766155606477,"sq":1.04,"sb":0.01,"itr":22.0,"itp":32,"lmvs":8.7441962E7,"smvs":401057.0,"lmvst":8.7441962E7,"smvst":401057.0,"pmvs":0.46,"pmvst":0.46},{"ci":"424181","ri":"424182","ti":"424192","tc":"Хельсингборг","wi":34.99,"ei":6.3,"as":490.0,"pi":"373201","pci":"1531","mi":"E","v":97637,"sc":3,"cc":3,"lpe":97.05,"lpr":172.01,"lq":1.0,"spr":171.739193236171,"sq":1.22,"sb":0.02,"itr":15.0,"itp":0,"lmvs":1.679454E7,"smvs":468998.0,"lmvst":1.679454E7,"smvst":468998.0,"pmvs":2.79,"pmvst":2.79},{"ci":"424181","ri":"424182","ti":"424193","tc":"Норрчепинг","wi":34.95,"ei":6.4,"as":480.0,"pi":"373201","pci":"1531","mi":"E","v":100237,"sc":3,"cc":3,"lpe":98.85,"lpr":173.37,"lq":1.0,"spr":173.024496443429,"sq":1.13,"sb":0.02,"itr":15.0,"itp":0,"lmvs":1.7378089E7,"smvs":165216.0,"lmvst":1.7378089E7,"smvst":165216.0,"pmvs":0.95,"pmvst":0.95},{"ci":"424181","ri":"424182","ti":"424194","tc":"Йенчепинг","wi":26.72,"ei":6.2,"as":460.6,"pi":"373201","pci":"1531","mi":"E","v":94173,"sc":2,"cc":2,"lpe":98.91,"lpr":160.37,"lq":1.0,"spr":160.293348411965,"sq":1.14,"sb":0.02,"itr":15.0,"itp":0,"lmvs":1.5102524E7,"smvs":157399.0,"lmvst":1.5102524E7,"smvst":157399.0,"pmvs":1.04,"pmvst":1.04},{"ci":"424181","ri":"424184","ti":"424195","tc":"Умео","wi":26.71,"ei":6.3,"as":456.0,"pi":"373201","pci":"1531","mi":"E","v":78452,"sc":2,"cc":2,"lpe":99.35,"lpr":112.97,"lq":1.0,"spr":113.28283243257,"sq":1.06,"sb":0.0,"itr":15.0,"itp":0,"lmvs":8862722.0,"smvs":82150.0,"lmvst":8862722.0,"smvst":82150.0,"pmvs":0.93,"pmvst":0.93},{"ci":"424181","ri":"424183","ti":"424190","tc":"Эребру","wi":26.88,"ei":6.4,"as":470.16,"pi":"373201","pci":"1531","mi":"E","v":104492,"sc":4,"cc":2,"lpe":99.59,"lpr":160.82,"lq":1.0,"spr":160.53978457681,"sq":1.0,"sb":0.0,"itr":15.0,"itp":0,"lmvs":1.6804403E7,"smvs":39618.0,"lmvst":1.6804403E7,"smvst":39618.0,"pmvs":0.24,"pmvst":0.24},{"ci":"424181","ri":"424183","ti":"424191","tc":"Вестерос","wi":27.95,"ei":6.5,"as":474.81,"pi":"373201","pci":"1531","mi":"E","v":109099,"sc":1,"cc":1,"lpe":99.8,"lpr":160.86,"lq":1.0,"spr":160.713775744966,"sq":1.0,"sb":0.0,"itr":15.0,"itp":0,"lmvs":1.7549665E7,"smvs":19146.0,"lmvst":1.7549665E7,"smvst":19146.0,"pmvs":0.11,"pmvst":0.11},{"ci":"2931","ri":"331858","ti":"331870","tc":"Великие Луки","wi":2.22,"ei":4.75,"as":142.19,"pi":"373201","pci":"1531","mi":"?","v":185227,"sc":0,"cc":0,"lpe":100.0,"lpr":8.29,"lq":1.0,"spr":8.29,"sq":1.0,"sb":0.0,"itr":25.0,"itp":1,"lmvs":1535532.0,"smvs":0.0,"lmvst":1535532.0,"smvst":0.0,"pmvs":0.0,"pmvst":0.0},{"ci":"424181","ri":"424182","ti":"424196","tc":"Лунд","wi":27.64,"ei":6.3,"as":485.1,"pi":"373201","pci":"1531","mi":"E","v":86429,"sc":1,"cc":1,"lpe":98.84,"lpr":160.38,"lq":1.0,"spr":160.028497610756,"sq":1.15,"sb":0.02,"itr":15.0,"itp":0,"lmvs":1.3861483E7,"smvs":130413.0,"lmvst":1.3861483E7,"smvst":130413.0,"pmvs":0.94,"pmvst":0.94},{"ci":"2931","ri":"331858","ti":"331871","tc":"Гатчина","wi":24.13,"ei":3.42,"as":268.0,"pi":"373201","pci":"1531","mi":"?","v":78940,"sc":0,"cc":0,"lpe":100.0,"lpr":132.05,"lq":1.0,"spr":132.05,"sq":1.0,"sb":0.0,"itr":25.0,"itp":1,"lmvs":1.0424027E7,"smvs":0.0,"lmvst":1.0424027E7,"smvst":0.0,"pmvs":0.0,"pmvst":0.0},{"ci":"424181","ri":"424182","ti":"424197","tc":"Бурос","wi":26.96,"ei":6.2,"as":470.4,"pi":"373201","pci":"1531","mi":"E","v":78912,"sc":1,"cc":1,"lpe":99.11,"lpr":160.92,"lq":1.0,"spr":160.734426196269,"sq":1.12,"sb":0.02,"itr":15.0,"itp":0,"lmvs":1.2698519E7,"smvs":98373.0,"lmvst":1.2698519E7,"smvst":98373.0,"pmvs":0.77,"pmvst":0.77},{"ci":"2931","ri":"331858","ti":"331872","tc":"Воркута","wi":8.06,"ei":4.62,"as":189.7,"pi":"373201","pci":"1531","mi":"?","v":94113,"sc":0,"cc":0,"lpe":100.0,"lpr":51.21,"lq":1.0,"spr":51.21,"sq":1.0,"sb":0.0,"itr":25.0,"itp":1,"lmvs":4819527.0,"smvs":0.0,"lmvst":4819527.0,"smvst":0.0,"pmvs":0.0,"pmvst":0.0},{"ci":"424181","ri":"424183","ti":"424198","tc":"Худдинге","wi":33.78,"ei":6.3,"as":470.0,"pi":"373201","pci":"1531","mi":"E","v":72279,"sc":1,"cc":1,"lpe":99.82,"lpr":168.38,"lq":1.0,"spr":168.324098009104,"sq":1.0,"sb":0.0,"itr":15.0,"itp":0,"lmvs":1.2170338E7,"smvs":17866.0,"lmvst":1.2170338E7,"smvst":17866.0,"pmvs":0.15,"pmvst":0.15},{"ci":"2931","ri":"331858","ti":"331873","tc":"Выборг","wi":8.14,"ei":3.78,"as":274.81,"pi":"373201","pci":"1531","mi":"?","v":32743,"sc":0,"cc":0,"lpe":100.0,"lpr":25.12,"lq":1.0,"spr":25.12,"sq":1.0,"sb":0.0,"itr":25.0,"itp":1,"lmvs":822504.0,"smvs":0.0,"lmvst":822504.0,"smvst":0.0,"pmvs":0.0,"pmvst":0.0},{"ci":"424181","ri":"424183","ti":"424199","tc":"Эскильстуна","wi":25.77,"ei":6.2,"as":442.23,"pi":"373201","pci":"1531","mi":"E","v":60688,"sc":2,"cc":2,"lpe":88.5,"lpr":159.48,"lq":1.17,"spr":158.385889796994,"sq":1.31,"sb":0.0,"itr":15.0,"itp":0,"lmvs":9678522.0,"smvs":1046631.0,"lmvst":9678522.0,"smvst":1046631.0,"pmvs":10.81,"pmvst":10.81},{"ci":"2931","ri":"2961","ti":"2964","tc":"Владивосток","wi":8.89,"ei":5.46,"as":329.3,"pi":"373201","pci":"1531","mi":"?","v":127096,"sc":0,"cc":0,"lpe":100.0,"lpr":97.34,"lq":1.0,"spr":97.34,"sq":1.0,"sb":0.0,"itr":10.0,"itp":1,"lmvs":1.2371525E7,"smvs":0.0,"lmvst":1.2371525E7,"smvst":0.0,"pmvs":0.0,"pmvst":0.0},{"ci":"2931","ri":"2961","ti":"2963","tc":"Якутск","wi":11.01,"ei":4.68,"as":602.3,"pi":"373201","pci":"1531","mi":"E","v":182625,"sc":1,"cc":1,"lpe":99.45,"lpr":136.11,"lq":1.0,"spr":136.08749486653,"sq":1.01,"sb":0.0,"itr":10.0,"itp":1,"lmvs":2.4857089E7,"smvs":132604.0,"lmvst":2.4857089E7,"smvst":132604.0,"pmvs":0.53,"pmvst":0.53},{"ci":"2931","ri":"2961","ti":"2962","tc":"Хабаровск","wi":20.15,"ei":6.15,"as":606.67,"pi":"373201","pci":"1531","mi":"?","v":865490,"sc":0,"cc":0,"lpe":100.0,"lpr":111.27,"lq":1.0,"spr":111.27,"sq":1.0,"sb":0.0,"itr":10.0,"itp":1,"lmvs":9.6303072E7,"smvs":0.0,"lmvst":9.6303072E7,"smvst":0.0,"pmvs":0.0,"pmvst":0.0},{"ci":"2931","ri":"2956","ti":"2960","tc":"Кемерово","wi":10.79,"ei":5.31,"as":346.85,"pi":"373201","pci":"1531","mi":"?","v":599481,"sc":0,"cc":0,"lpe":100.0,"lpr":63.98,"lq":1.0,"spr":63.98,"sq":1.0,"sb":0.0,"itr":30.0,"itp":1,"lmvs":3.8354794E7,"smvs":0.0,"lmvst":3.8354794E7,"smvst":0.0,"pmvs":0.0,"pmvst":0.0},{"ci":"2931","ri":"331858","ti":"331867","tc":"Псков","wi":24.44,"ei":5.07,"as":294.7,"pi":"373201","pci":"1531","mi":"?","v":171764,"sc":0,"cc":0,"lpe":100.0,"lpr":138.54,"lq":1.0,"spr":138.54,"sq":1.0,"sb":0.0,"itr":25.0,"itp":1,"lmvs":2.3796185E7,"smvs":0.0,"lmvst":2.3796185E7,"smvst":0.0,"pmvs":0.0,"pmvst":0.0},{"ci":"2931","ri":"331858","ti":"331868","tc":"Северодвинск","wi":6.24,"ei":4.76,"as":142.7,"pi":"373201","pci":"1531","mi":"?","v":212485,"sc":0,"cc":0,"lpe":100.0,"lpr":61.34,"lq":1.0,"spr":61.34,"sq":1.0,"sb":0.0,"itr":25.0,"itp":1,"lmvs":1.303383E7,"smvs":0.0,"lmvst":1.303383E7,"smvst":0.0,"pmvs":0.0,"pmvst":0.0},{"ci":"2931","ri":"331858","ti":"331869","tc":"Ухта","wi":7.4,"ei":4.21,"as":161.5,"pi":"373201","pci":"1531","mi":"?","v":106573,"sc":0,"cc":0,"lpe":100.0,"lpr":35.01,"lq":1.0,"spr":35.01,"sq":1.0,"sb":0.0,"itr":25.0,"itp":1,"lmvs":3731121.0,"smvs":0.0,"lmvst":3731121.0,"smvst":0.0,"pmvs":0.0,"pmvst":0.0},{"ci":"2931","ri":"331858","ti":"331863","tc":"Петрозаводск","wi":15.53,"ei":4.42,"as":210.8,"pi":"373201","pci":"1531","mi":"?","v":215975,"sc":0,"cc":0,"lpe":100.0,"lpr":88.77,"lq":1.0,"spr":88.77,"sq":1.0,"sb":0.0,"itr":25.0,"itp":1,"lmvs":1.9172101E7,"smvs":0.0,"lmvst":1.9172101E7,"smvst":0.0,"pmvs":0.0,"pmvst":0.0},{"ci":"15906","ri":"15922","ti":"3035","tc":"Ницца","wi":58.37,"ei":7.76,"as":807.0,"pi":"373201","pci":"1531","mi":"E","v":261029,"sc":3,"cc":3,"lpe":98.38,"lpr":275.6,"lq":1.0,"spr":276.092626489777,"sq":1.15,"sb":0.03,"itr":17.0,"itp":13,"lmvs":7.1939592E7,"smvs":1294011.0,"lmvst":7.1939592E7,"smvst":1294011.0,"pmvs":1.8,"pmvst":1.8},{"ci":"2931","ri":"331858","ti":"331864","tc":"Вологда","wi":16.16,"ei":6.31,"as":221.1,"pi":"373201","pci":"1531","mi":"E","v":184352,"sc":1,"cc":1,"lpe":99.46,"lpr":76.09,"lq":1.0,"spr":76.078662992536,"sq":1.01,"sb":0.0,"itr":25.0,"itp":1,"lmvs":1.4027344E7,"smvs":73658.0,"lmvst":1.4027344E7,"smvst":73658.0,"pmvs":0.53,"pmvst":0.53},{"ci":"15906","ri":"15922","ti":"3034","tc":"Тулуза","wi":46.98,"ei":5.0,"as":388.33,"pi":"373201","pci":"1531","mi":"E","v":268331,"sc":3,"cc":3,"lpe":98.5,"lpr":264.18,"lq":1.0,"spr":264.844013848568,"sq":1.15,"sb":0.03,"itr":17.0,"itp":13,"lmvs":7.0887684E7,"smvs":1241491.0,"lmvst":7.0887684E7,"smvst":1241491.0,"pmvs":1.75,"pmvst":1.75},{"ci":"2931","ri":"331858","ti":"331865","tc":"Сыктывкар","wi":15.83,"ei":6.7,"as":209.4,"pi":"373201","pci":"1531","mi":"?","v":245434,"sc":0,"cc":0,"lpe":100.0,"lpr":77.97,"lq":1.0,"spr":77.97,"sq":1.0,"sb":0.0,"itr":25.0,"itp":1,"lmvs":1.9136489E7,"smvs":0.0,"lmvst":1.9136489E7,"smvst":0.0,"pmvs":0.0,"pmvst":0.0},{"ci":"15906","ri":"15922","ti":"3033","tc":"Лион","wi":48.71,"ei":6.0,"as":450.0,"pi":"373201","pci":"1531","mi":"E","v":322918,"sc":3,"cc":3,"lpe":98.71,"lpr":266.24,"lq":1.0,"spr":266.485760471699,"sq":1.12,"sb":0.03,"itr":17.0,"itp":13,"lmvs":8.5973688E7,"smvs":1188421.0,"lmvst":8.5973688E7,"smvst":1188421.0,"pmvs":1.38,"pmvst":1.38},{"ci":"2931","ri":"331858","ti":"331866","tc":"Великий Новгород","wi":16.19,"ei":8.65,"as":559.5,"pi":"373201","pci":"1531","mi":"E","v":95886,"sc":3,"cc":3,"lpe":89.26,"lpr":98.71,"lq":1.0,"spr":103.411280687483,"sq":1.99,"sb":0.03,"itr":25.0,"itp":1,"lmvs":9464907.0,"smvs":1467318.0,"lmvst":9464907.0,"smvst":1467318.0,"pmvs":15.5,"pmvst":15.5},{"ci":"15906","ri":"15922","ti":"3032","tc":"Марсель","wi":47.83,"ei":6.0,"as":448.87,"pi":"373201","pci":"1531","mi":"E","v":610518,"sc":7,"cc":5,"lpe":94.22,"lpr":267.05,"lq":1.0,"spr":267.055585994189,"sq":1.22,"sb":0.01,"itr":17.0,"itp":13,"lmvs":1.63038832E8,"smvs":9427055.0,"lmvst":1.63038832E8,"smvst":9427055.0,"pmvs":5.78,"pmvst":5.78},{"ci":"15906","ri":"15923","ti":"3031","tc":"Париж","wi":47.6,"ei":7.77,"as":378.0,"pi":"373201","pci":"1531","mi":"E","v":1582838,"sc":4,"cc":4,"lpe":98.32,"lpr":261.24,"lq":1.0,"spr":262.461753382216,"sq":1.15,"sb":0.01,"itr":21.0,"itp":13,"lmvs":4.13500599E8,"smvs":8880648.0,"lmvst":4.13500599E8,"smvst":8880648.0,"pmvs":2.15,"pmvst":2.15},{"ci":"2931","ri":"331858","ti":"331860","tc":"Архангельск","wi":18.29,"ei":4.91,"as":316.1,"pi":"373201","pci":"1531","mi":"E","v":350215,"sc":1,"cc":1,"lpe":74.65,"lpr":128.09,"lq":1.18,"spr":153.919382893366,"sq":2.23,"sb":0.34,"itr":25.0,"itp":1,"lmvs":4.4859039E7,"smvs":2.0417604E7,"lmvst":4.4859039E7,"smvst":2.0417604E7,"pmvs":45.52,"pmvst":45.52},{"ci":"2931","ri":"331858","ti":"331861","tc":"Череповец","wi":16.57,"ei":12.83,"as":302.48,"pi":"373201","pci":"1531","mi":"?","v":388314,"sc":0,"cc":0,"lpe":100.0,"lpr":77.89,"lq":1.0,"spr":77.89,"sq":1.0,"sb":0.0,"itr":25.0,"itp":1,"lmvs":3.0245777E7,"smvs":0.0,"lmvst":3.0245777E7,"smvst":0.0,"pmvs":0.0,"pmvst":0.0},{"ci":"2931","ri":"331858","ti":"331862","tc":"Мурманск","wi":22.54,"ei":5.59,"as":546.9,"pi":"373201","pci":"1531","mi":"?","v":338071,"sc":0,"cc":0,"lpe":100.0,"lpr":162.1,"lq":1.0,"spr":162.1,"sq":1.0,"sb":0.0,"itr":25.0,"itp":1,"lmvs":5.4801309E7,"smvs":0.0,"lmvst":5.4801309E7,"smvst":0.0,"pmvs":0.0,"pmvst":0.0},{"ci":"15734","ri":"15735","ti":"15740","tc":"Могилёв","wi":22.02,"ei":4.69,"as":413.07,"pi":"373201","pci":"1531","mi":"E","v":333308,"sc":3,"cc":3,"lpe":99.28,"lpr":151.78,"lq":1.0,"spr":151.806867401923,"sq":1.07,"sb":0.0,"itr":30.0,"itp":5,"lmvs":5.0589488E7,"smvs":373199.0,"lmvst":5.0589488E7,"smvst":373199.0,"pmvs":0.74,"pmvst":0.74},{"ci":"2931","ri":"331858","ti":"331859","tc":"Калининград","wi":37.95,"ei":7.19,"as":1002.4,"pi":"373201","pci":"1531","mi":"E","v":796373,"sc":1,"cc":1,"lpe":99.84,"lpr":161.46,"lq":1.0,"spr":161.451429895288,"sq":1.0,"sb":0.0,"itr":25.0,"itp":1,"lmvs":1.28582385E8,"smvs":198907.0,"lmvst":1.28582385E8,"smvst":198907.0,"pmvs":0.15,"pmvst":0.15},{"ci":"15905","ri":"15920","ti":"3046","tc":"Кёльн","wi":49.72,"ei":7.0,"as":374.0,"pi":"373201","pci":"1531","mi":"E","v":703136,"sc":3,"cc":3,"lpe":99.83,"lpr":272.84,"lq":1.0,"spr":272.958117576116,"sq":1.02,"sb":0.0,"itr":22.0,"itp":32,"lmvs":1.91843626E8,"smvs":409187.0,"lmvst":1.91843626E8,"smvst":409187.0,"pmvs":0.21,"pmvst":0.21},{"ci":"15905","ri":"15920","ti":"3045","tc":"Мюнхен","wi":53.01,"ei":5.0,"as":324.0,"pi":"373201","pci":"1531","mi":"E","v":795604,"sc":4,"cc":4,"lpe":99.22,"lpr":261.03,"lq":1.0,"spr":261.578737361803,"sq":1.09,"sb":0.01,"itr":22.0,"itp":32,"lmvs":2.07676512E8,"smvs":2056454.0,"lmvst":2.07676512E8,"smvst":2056454.0,"pmvs":0.99,"pmvst":0.99},{"ci":"15905","ri":"15920","ti":"3044","tc":"Гамбург","wi":63.08,"ei":7.98,"as":479.0,"pi":"373201","pci":"1531","mi":"E","v":1146560,"sc":6,"cc":6,"lpe":96.31,"lpr":388.31,"lq":1.0,"spr":388.926262498256,"sq":1.14,"sb":0.0,"itr":22.0,"itp":32,"lmvs":4.45220714E8,"smvs":1.7135226E7,"lmvst":4.45220714E8,"smvst":1.7135226E7,"pmvs":3.85,"pmvst":3.85},{"ci":"15905","ri":"15921","ti":"3043","tc":"Берлин","wi":38.04,"ei":8.74,"as":423.0,"pi":"373201","pci":"1531","mi":"E","v":2942381,"sc":2,"cc":2,"lpe":99.9,"lpr":170.94,"lq":1.0,"spr":170.996817930785,"sq":1.01,"sb":0.0,"itr":22.0,"itp":32,"lmvs":5.02970608E8,"smvs":670151.0,"lmvst":5.02970608E8,"smvst":670151.0,"pmvs":0.13,"pmvst":0.13},{"ci":"15906","ri":"15923","ti":"3041","tc":"Нант","wi":34.42,"ei":7.0,"as":453.0,"pi":"373201","pci":"1531","mi":"E","v":215119,"sc":2,"cc":2,"lpe":97.21,"lpr":167.88,"lq":1.0,"spr":169.984509597014,"sq":1.26,"sb":0.02,"itr":21.0,"itp":13,"lmvs":3.6114178E7,"smvs":1460306.0,"lmvst":3.6114178E7,"smvst":1460306.0,"pmvs":4.04,"pmvst":4.04},{"ci":"15906","ri":"15923","ti":"3040","tc":"Реймс","wi":37.43,"ei":6.0,"as":565.0,"pi":"373201","pci":"1531","mi":"E","v":134496,"sc":3,"cc":3,"lpe":94.05,"lpr":186.94,"lq":1.0,"spr":191.768991196764,"sq":1.57,"sb":0.03,"itr":21.0,"itp":13,"lmvs":2.5142682E7,"smvs":2145470.0,"lmvst":2.5142682E7,"smvst":2145470.0,"pmvs":8.53,"pmvst":8.53},{"ci":"15906","ri":"15923","ti":"3039","tc":"Гавр","wi":54.46,"ei":6.0,"as":457.0,"pi":"373201","pci":"1531","mi":"E","v":134838,"sc":2,"cc":2,"lpe":95.55,"lpr":271.65,"lq":1.0,"spr":273.875633723431,"sq":1.42,"sb":0.03,"itr":21.0,"itp":13,"lmvs":3.6628743E7,"smvs":1930079.0,"lmvst":3.6628743E7,"smvst":1930079.0,"pmvs":5.27,"pmvst":5.27},{"ci":"15906","ri":"15923","ti":"3038","tc":"Ренн","wi":33.4,"ei":6.0,"as":384.38,"pi":"373201","pci":"1531","mi":"E","v":168547,"sc":2,"cc":2,"lpe":95.85,"lpr":164.61,"lq":1.0,"spr":166.744300818169,"sq":1.39,"sb":0.02,"itr":21.0,"itp":13,"lmvs":2.7744522E7,"smvs":1511128.0,"lmvst":2.7744522E7,"smvst":1511128.0,"pmvs":5.45,"pmvst":5.45},{"ci":"15906","ri":"15922","ti":"3037","tc":"Бордо","wi":46.83,"ei":6.0,"as":468.0,"pi":"373201","pci":"1531","mi":"E","v":157195,"sc":3,"cc":3,"lpe":96.74,"lpr":261.54,"lq":1.0,"spr":262.34634065969,"sq":1.3,"sb":0.06,"itr":17.0,"itp":13,"lmvs":4.111278E7,"smvs":1467029.0,"lmvst":4.111278E7,"smvst":1467029.0,"pmvs":3.57,"pmvst":3.57},{"ci":"15906","ri":"15923","ti":"3036","tc":"Страсбург","wi":51.02,"ei":8.0,"as":490.0,"pi":"373201","pci":"1531","mi":"E","v":192279,"sc":2,"cc":2,"lpe":93.76,"lpr":267.85,"lq":1.0,"spr":273.132948215874,"sq":1.57,"sb":0.03,"itr":21.0,"itp":13,"lmvs":5.150193E7,"smvs":4229520.0,"lmvst":5.150193E7,"smvst":4229520.0,"pmvs":8.21,"pmvst":8.21},{"ci":"15734","ri":"15735","ti":"15741","tc":"Витебск","wi":23.61,"ei":8.41,"as":495.02,"pi":"373201","pci":"1531","mi":"E","v":282275,"sc":4,"cc":4,"lpe":98.62,"lpr":163.47,"lq":1.0,"spr":163.660279585511,"sq":1.08,"sb":0.0,"itr":30.0,"itp":5,"lmvs":4.6143494E7,"smvs":690491.0,"lmvst":4.6143494E7,"smvst":690491.0,"pmvs":1.5,"pmvst":1.5},{"ci":"15734","ri":"15735","ti":"16322","tc":"Бобруйск","wi":10.62,"ei":6.43,"as":359.86,"pi":"373201","pci":"1531","mi":"E","v":68651,"sc":1,"cc":1,"lpe":98.54,"lpr":85.35,"lq":1.0,"spr":85.7818946555767,"sq":1.19,"sb":0.01,"itr":30.0,"itp":5,"lmvs":5859363.0,"smvs":115197.0,"lmvst":5859363.0,"smvst":115197.0,"pmvs":1.97,"pmvst":1.97},{"ci":"15905","ri":"15920","ti":"3053","tc":"Ганновер","wi":53.9,"ei":6.0,"as":346.0,"pi":"373201","pci":"1531","mi":"E","v":367393,"sc":2,"cc":2,"lpe":99.7,"lpr":270.34,"lq":1.0,"spr":270.673072595286,"sq":1.04,"sb":0.01,"itr":22.0,"itp":32,"lmvs":9.9321024E7,"smvs":420332.0,"lmvst":9.9321024E7,"smvst":420332.0,"pmvs":0.42,"pmvst":0.42},{"ci":"15905","ri":"15920","ti":"3052","tc":"Бремен","wi":47.04,"ei":5.0,"as":323.0,"pi":"373201","pci":"1531","mi":"E","v":214458,"sc":3,"cc":3,"lpe":97.61,"lpr":269.07,"lq":1.0,"spr":274.325833776311,"sq":1.22,"sb":0.01,"itr":22.0,"itp":32,"lmvs":5.7704214E7,"smvs":2506286.0,"lmvst":5.7704214E7,"smvst":2506286.0,"pmvs":4.34,"pmvst":4.34},{"ci":"15905","ri":"15920","ti":"3051","tc":"Дюссельдорф","wi":49.5,"ei":5.0,"as":327.0,"pi":"373201","pci":"1531","mi":"E","v":357316,"sc":2,"cc":2,"lpe":99.68,"lpr":268.41,"lq":1.0,"spr":268.666822252572,"sq":1.04,"sb":0.01,"itr":22.0,"itp":32,"lmvs":9.5907188E7,"smvs":398670.0,"lmvst":9.5907188E7,"smvst":398670.0,"pmvs":0.42,"pmvst":0.42},{"ci":"15905","ri":"15920","ti":"3050","tc":"Штутгарт","wi":50.1,"ei":6.0,"as":383.0,"pi":"373201","pci":"1531","mi":"E","v":418481,"sc":3,"cc":3,"lpe":91.44,"lpr":189.22,"lq":1.0,"spr":217.777993696249,"sq":1.67,"sb":0.09,"itr":22.0,"itp":32,"lmvs":7.9184975E7,"smvs":1.8729212E7,"lmvst":7.9184975E7,"smvst":1.8729212E7,"pmvs":23.65,"pmvst":23.65},{"ci":"15905","ri":"15920","ti":"3049","tc":"Дортмунд","wi":54.84,"ei":5.0,"as":319.18,"pi":"373201","pci":"1531","mi":"E","v":427863,"sc":2,"cc":2,"lpe":99.73,"lpr":271.99,"lq":1.0,"spr":272.215119021743,"sq":1.03,"sb":0.0,"itr":22.0,"itp":32,"lmvs":1.16374457E8,"smvs":410531.0,"lmvst":1.16374457E8,"smvst":410531.0,"pmvs":0.35,"pmvst":0.35},{"ci":"15905","ri":"15920","ti":"3048","tc":"Эссен","wi":51.09,"ei":5.0,"as":375.0,"pi":"373201","pci":"1531","mi":"E","v":245729,"sc":2,"cc":2,"lpe":99.52,"lpr":269.19,"lq":1.0,"spr":269.518971997607,"sq":1.05,"sb":0.01,"itr":22.0,"itp":32,"lmvs":6.614779E7,"smvs":398347.0,"lmvst":6.614779E7,"smvst":398347.0,"pmvs":0.6,"pmvst":0.6},{"ci":"15905","ri":"15920","ti":"3047","tc":"Франкфурт","wi":65.6,"ei":7.0,"as":380.0,"pi":"373201","pci":"1531","mi":"E","v":347240,"sc":4,"cc":4,"lpe":90.17,"lpr":345.35,"lq":1.0,"spr":353.398340052989,"sq":1.43,"sb":0.01,"itr":22.0,"itp":32,"lmvs":1.19919334E8,"smvs":1.4582776E7,"lmvst":1.19919334E8,"smvst":1.4582776E7,"pmvs":12.16,"pmvst":12.16},{"ci":"15906","ri":"15922","ti":"15960","tc":"Аяччо","wi":33.3,"ei":5.0,"as":715.0,"pi":"373201","pci":"1531","mi":"E","v":43262,"sc":4,"cc":4,"lpe":89.68,"lpr":134.49,"lq":1.35,"spr":142.195899865933,"sq":2.42,"sb":0.19,"itr":17.0,"itp":13,"lmvs":5818306.0,"smvs":933822.0,"lmvst":5818306.0,"smvst":933822.0,"pmvs":16.05,"pmvst":16.05},{"ci":"2931","ri":"2956","ti":"10716","tc":"Томск","wi":15.91,"ei":6.64,"as":252.1,"pi":"373201","pci":"1531","mi":"?","v":547104,"sc":0,"cc":0,"lpe":100.0,"lpr":82.77,"lq":1.0,"spr":82.77,"sq":1.0,"sb":0.0,"itr":30.0,"itp":1,"lmvs":4.5283798E7,"smvs":0.0,"lmvst":4.5283798E7,"smvst":0.0,"pmvs":0.0,"pmvst":0.0},{"ci":"15906","ri":"15923","ti":"15961","tc":"Дижон","wi":46.77,"ei":6.0,"as":410.0,"pi":"373201","pci":"1531","mi":"E","v":109099,"sc":2,"cc":2,"lpe":93.58,"lpr":264.59,"lq":1.0,"spr":268.54851474349,"sq":1.6,"sb":0.04,"itr":21.0,"itp":13,"lmvs":2.8866504E7,"smvs":2285100.0,"lmvst":2.8866504E7,"smvst":2285100.0,"pmvs":7.92,"pmvst":7.92},{"ci":"17597","ri":"17598","ti":"17599","tc":"Мадрид","wi":47.49,"ei":5.0,"as":354.0,"pi":"373201","pci":"1531","mi":"E","v":1792900,"sc":3,"cc":3,"lpe":97.92,"lpr":264.71,"lq":1.0,"spr":264.885819415472,"sq":1.08,"sb":0.0,"itr":20.0,"itp":0,"lmvs":4.74598559E8,"smvs":1.0186877E7,"lmvst":4.74598559E8,"smvst":1.0186877E7,"pmvs":2.15,"pmvst":2.15},{"ci":"422653","ri":"422655","ti":"422660","tc":"Нью-Йорк","wi":79.78,"ei":9.46,"as":2502.0,"pi":"373201","pci":"1531","mi":"E","v":6680455,"sc":27,"cc":23,"lpe":79.9,"lpr":270.15,"lq":3.19,"spr":314.907141866834,"sq":4.69,"sb":0.04,"itr":24.0,"itp":0,"lmvs":1.804724918E9,"smvs":6.61747781E8,"lmvst":1.804724918E9,"smvst":6.61747781E8,"pmvs":36.67,"pmvst":36.67},{"ci":"424181","ri":"424183","ti":"424200","tc":"Накка","wi":33.22,"ei":6.1,"as":450.8,"pi":"373201","pci":"1531","mi":"E","v":65905,"sc":2,"cc":2,"lpe":99.85,"lpr":168.99,"lq":1.0,"spr":169.09662256278,"sq":1.0,"sb":0.0,"itr":15.0,"itp":0,"lmvs":1.1137286E7,"smvs":23733.0,"lmvst":1.1137286E7,"smvst":23733.0,"pmvs":0.21,"pmvst":0.21},{"ci":"422653","ri":"422659","ti":"422661","tc":"Лос-Анджелес","wi":58.91,"ei":7.0,"as":1299.6,"pi":"373201","pci":"1531","mi":"E","v":1535626,"sc":12,"cc":12,"lpe":92.7,"lpr":282.19,"lq":1.0,"spr":281.890523460791,"sq":1.6,"sb":0.02,"itr":39.0,"itp":0,"lmvs":4.33338301E8,"smvs":3.1173812E7,"lmvst":4.33338301E8,"smvst":3.1173812E7,"pmvs":7.19,"pmvst":7.19},{"ci":"424181","ri":"424184","ti":"424201","tc":"Евле","wi":26.48,"ei":6.0,"as":450.8,"pi":"373201","pci":"1531","mi":"E","v":66731,"sc":1,"cc":1,"lpe":99.99,"lpr":117.95,"lq":1.0,"spr":117.941315880176,"sq":1.0,"sb":0.0,"itr":15.0,"itp":0,"lmvs":7870921.0,"smvs":208.0,"lmvst":7870921.0,"smvst":208.0,"pmvs":0.0,"pmvst":0.0},{"ci":"422653","ri":"422657","ti":"422662","tc":"Чикаго","wi":65.52,"ei":7.0,"as":1059.0,"pi":"373201","pci":"1531","mi":"E","v":1323209,"sc":4,"cc":4,"lpe":95.38,"lpr":378.76,"lq":1.0,"spr":383.008800907491,"sq":1.42,"sb":0.02,"itr":33.0,"itp":0,"lmvs":5.01178641E8,"smvs":2.8776505E7,"lmvst":5.01178641E8,"smvst":2.8776505E7,"pmvs":5.74,"pmvst":5.74},{"ci":"424181","ri":"424184","ti":"424202","tc":"Сундсвалль","wi":26.51,"ei":6.1,"as":450.8,"pi":"373201","pci":"1531","mi":"?","v":70118,"sc":0,"cc":0,"lpe":100.0,"lpr":151.95,"lq":1.0,"spr":151.95,"sq":1.0,"sb":0.0,"itr":15.0,"itp":0,"lmvs":1.065443E7,"smvs":0.0,"lmvst":1.065443E7,"smvst":0.0,"pmvs":0.0,"pmvst":0.0},{"ci":"422653","ri":"422658","ti":"422663","tc":"Хьюстон","wi":62.72,"ei":7.0,"as":1148.0,"pi":"373201","pci":"1531","mi":"E","v":1459699,"sc":11,"cc":10,"lpe":81.87,"lpr":351.7,"lq":3.25,"spr":361.032067090544,"sq":4.23,"sb":0.02,"itr":31.0,"itp":0,"lmvs":5.13376138E8,"smvs":1.06697103E8,"lmvst":5.13376138E8,"smvst":1.06697103E8,"pmvs":20.78,"pmvst":20.78},{"ci":"424181","ri":"424184","ti":"424203","tc":"Лулео","wi":26.28,"ei":6.0,"as":441.0,"pi":"373201","pci":"1531","mi":"?","v":49201,"sc":0,"cc":0,"lpe":100.0,"lpr":157.39,"lq":1.0,"spr":157.39,"sq":1.0,"sb":0.0,"itr":15.0,"itp":0,"lmvs":7743745.0,"smvs":0.0,"lmvst":7743745.0,"smvst":0.0,"pmvs":0.0,"pmvst":0.0},{"ci":"2931","ri":"2932","ti":"2933","tc":"Москва","wi":22.52,"ei":5.34,"as":224.4,"pi":"373201","pci":"1531","mi":"E","v":8017788,"sc":1,"cc":1,"lpe":97.77,"lpr":160.25,"lq":1.0,"spr":163.563364920599,"sq":1.1,"sb":0.01,"itr":30.0,"itp":1,"lmvs":1.284850527E9,"smvs":5.5218024E7,"lmvst":1.284850527E9,"smvst":5.5218024E7,"pmvs":4.3,"pmvst":4.3},{"ci":"15734","ri":"15735","ti":"15739","tc":"Гродно","wi":20.66,"ei":5.39,"as":398.09,"pi":"373201","pci":"1531","mi":"E","v":189920,"sc":2,"cc":2,"lpe":99.29,"lpr":148.02,"lq":1.0,"spr":148.111290332772,"sq":1.07,"sb":0.0,"itr":30.0,"itp":5,"lmvs":2.8111958E7,"smvs":216933.0,"lmvst":2.8111958E7,"smvst":216933.0,"pmvs":0.77,"pmvst":0.77},{"ci":"15734","ri":"15735","ti":"15738","tc":"Гомель","wi":23.3,"ei":7.48,"as":472.9,"pi":"373201","pci":"1531","mi":"E","v":309672,"sc":3,"cc":3,"lpe":99.1,"lpr":159.48,"lq":1.0,"spr":159.500079955566,"sq":1.05,"sb":0.0,"itr":30.0,"itp":5,"lmvs":4.9386491E7,"smvs":450697.0,"lmvst":4.9386491E7,"smvst":450697.0,"pmvs":0.91,"pmvst":0.91},{"ci":"2931","ri":"2932","ti":"2938","tc":"Иваново","wi":8.2,"ei":3.8,"as":209.7,"pi":"373201","pci":"1531","mi":"?","v":342467,"sc":0,"cc":0,"lpe":100.0,"lpr":62.47,"lq":1.0,"spr":62.47,"sq":1.0,"sb":0.0,"itr":30.0,"itp":1,"lmvs":2.1393913E7,"smvs":0.0,"lmvst":2.1393913E7,"smvst":0.0,"pmvs":0.0,"pmvst":0.0},{"ci":"15734","ri":"15735","ti":"15737","tc":"Брест","wi":21.82,"ei":8.8,"as":448.97,"pi":"373201","pci":"1531","mi":"E","v":367979,"sc":3,"cc":3,"lpe":99.24,"lpr":155.41,"lq":1.0,"spr":155.38095798945,"sq":1.04,"sb":0.0,"itr":30.0,"itp":5,"lmvs":5.7187616E7,"smvs":423939.0,"lmvst":5.7187616E7,"smvst":423939.0,"pmvs":0.74,"pmvst":0.74},{"ci":"2931","ri":"2932","ti":"2937","tc":"Липецк","wi":18.09,"ei":13.68,"as":415.06,"pi":"373201","pci":"1531","mi":"?","v":821316,"sc":0,"cc":0,"lpe":100.0,"lpr":128.98,"lq":1.0,"spr":128.98,"sq":1.0,"sb":0.0,"itr":30.0,"itp":1,"lmvs":1.05933338E8,"smvs":0.0,"lmvst":1.05933338E8,"smvst":0.0,"pmvs":0.0,"pmvst":0.0},{"ci":"15734","ri":"15735","ti":"15736","tc":"Минск","wi":28.55,"ei":12.08,"as":459.6,"pi":"373201","pci":"1531","mi":"E","v":2806927,"sc":4,"cc":4,"lpe":99.93,"lpr":161.81,"lq":1.0,"spr":161.83466777369,"sq":1.0,"sb":0.0,"itr":30.0,"itp":5,"lmvs":4.54188858E8,"smvs":387173.0,"lmvst":4.54188858E8,"smvst":387173.0,"pmvs":0.09,"pmvst":0.09},{"ci":"2931","ri":"2932","ti":"2936","tc":"Ярославль","wi":9.51,"ei":6.34,"as":395.11,"pi":"373201","pci":"1531","mi":"?","v":1978748,"sc":0,"cc":0,"lpe":100.0,"lpr":29.34,"lq":1.0,"spr":29.34,"sq":1.0,"sb":0.0,"itr":30.0,"itp":1,"lmvs":5.8056466E7,"smvs":0.0,"lmvst":5.8056466E7,"smvst":0.0,"pmvs":0.0,"pmvst":0.0},{"ci":"2931","ri":"2932","ti":"2935","tc":"Воронеж","wi":9.03,"ei":5.37,"as":254.79,"pi":"373201","pci":"1531","mi":"?","v":165247,"sc":0,"cc":0,"lpe":100.0,"lpr":83.23,"lq":1.0,"spr":83.23,"sq":1.0,"sb":0.0,"itr":30.0,"itp":1,"lmvs":1.3753508E7,"smvs":0.0,"lmvst":1.3753508E7,"smvst":0.0,"pmvs":0.0,"pmvst":0.0},{"ci":"2931","ri":"331858","ti":"2934","tc":"Санкт-Петербург","wi":31.91,"ei":5.73,"as":592.8,"pi":"373201","pci":"1531","mi":"E","v":5200901,"sc":2,"cc":2,"lpe":99.96,"lpr":160.53,"lq":1.0,"spr":160.491909840237,"sq":1.0,"sb":0.0,"itr":25.0,"itp":1,"lmvs":8.34900638E8,"smvs":135857.0,"lmvst":8.34900638E8,"smvst":135857.0,"pmvs":0.02,"pmvst":0.02}]