[{"cn":"Rastajzlik Ltd.","pi":"1510","ui":"9080469","ci":"424181","ri":"424183","ti":"424185","t":255,"r":255,"q":14.25,"p":8750.0,"mot":"U","mo":0},{"cn":"Don Pedro Invest","pi":"1510","ui":"9008856","ci":"424181","ri":"424183","ti":"424199","t":366236,"r":362893,"q":31.47,"p":10000.0,"mot":"U","mo":0},{"cn":"Олимп Трейд","pi":"1510","ui":"7166595","ci":"2931","ri":"2939","ti":"2942","t":1487875,"r":1486325,"q":23.4,"p":28000.0,"mot":"U","mo":0},{"cn":"frania82 Инвест","pi":"1510","ui":"8475331","ci":"17597","ri":"17598","ti":"17600","t":50932,"r":50932,"q":13.14,"p":57000.0,"mot":"U","mo":0},{"cn":"BPT Ltd","pi":"1510","ui":"8496124","ci":"2931","ri":"2961","ti":"2964","t":94769,"r":94769,"q":13.76,"p":76500.0,"mot":"U","mo":0},{"cn":"AVALON","pi":"1510","ui":"8607486","ci":"401798","ri":"401825","ti":"401940","t":2194289,"r":2194289,"q":31.37,"p":175000.0,"mot":"L","mo":500}]