[{"ci":"422626","et":100.0},{"ci":"422632","et":100.0},{"ci":"7087","et":25.0},{"ci":"7084","et":25.0},{"ci":"423480","et":90.0},{"ci":"7076","et":80.0},{"ci":"359845","et":90.0},{"ci":"424653","et":80.0},{"ci":"401959","et":90.0},{"ci":"359839","et":90.0},{"ci":"424625","et":110.0},{"ci":"310397","et":80.0},{"ci":"424619","et":80.0},{"ci":"424070","et":90.0},{"ci":"401870","et":80.0},{"ci":"423004","et":120.0},{"ci":"7073","et":130.0},{"ci":"7086","et":25.0},{"ci":"422046","et":170.0},{"ci":"7081","et":80.0},{"ci":"401936","et":80.0},{"ci":"401961","et":170.0},{"ci":"401953","et":90.0},{"ci":"424338","et":70.0},{"ci":"375147","et":70.0},{"ci":"375151","et":70.0},{"ci":"423854","et":100.0},{"ci":"423848","et":140.0},{"ci":"335168","et":80.0},{"ci":"335171","et":80.0},{"ci":"424266","et":50.0},{"ci":"424336","et":80.0},{"ci":"422683","et":180.0},{"ci":"423846","et":140.0},{"ci":"424626","et":80.0},{"ci":"424623","et":110.0},{"ci":"424197","et":60.0},{"ci":"310399","et":80.0},{"ci":"422409","et":40.0},{"ci":"423206","et":50.0},{"ci":"423113","et":110.0},{"ci":"375146","et":70.0},{"ci":"423199","et":60.0},{"ci":"422682","et":40.0},{"ci":"424340","et":80.0},{"ci":"424341","et":80.0},{"ci":"422965","et":120.0},{"ci":"422966","et":120.0},{"ci":"424191","et":100.0},{"ci":"325652","et":120.0},{"ci":"2964","et":100.0},{"ci":"2947","et":15.0},{"ci":"422051","et":170.0},{"ci":"2935","et":60.0},{"ci":"423202","et":40.0},{"ci":"359840","et":90.0},{"ci":"422189","et":100.0},{"ci":"422614","et":100.0},{"ci":"423204","et":50.0},{"ci":"423807","et":50.0},{"ci":"424620","et":80.0},{"ci":"424335","et":70.0},{"ci":"424186","et":60.0},{"ci":"401867","et":200.0},{"ci":"423853","et":140.0},{"ci":"359846","et":90.0},{"ci":"422633","et":15.0},{"ci":"422193","et":100.0},{"ci":"401865","et":30.0},{"ci":"423855","et":140.0},{"ci":"401861","et":30.0},{"ci":"401943","et":90.0},{"ci":"401843","et":25.0},{"ci":"422956","et":10.0},{"ci":"325648","et":60.0},{"ci":"401957","et":90.0},{"ci":"423108","et":90.0},{"ci":"401951","et":90.0},{"ci":"401960","et":90.0},{"ci":"422672","et":70.0},{"ci":"424675","et":90.0},{"ci":"401946","et":50.0},{"ci":"401945","et":50.0},{"ci":"424201","et":60.0},{"ci":"2951","et":120.0},{"ci":"7068","et":40.0},{"ci":"2938","et":60.0},{"ci":"424652","et":110.0},{"ci":"422671","et":150.0},{"ci":"401882","et":50.0},{"ci":"401838","et":25.0},{"ci":"401872","et":80.0},{"ci":"423537","et":50.0},{"ci":"422049","et":140.0},{"ci":"424194","et":60.0},{"ci":"2943","et":20.0},{"ci":"423114","et":110.0},{"ci":"422191","et":100.0},{"ci":"422963","et":120.0},{"ci":"423856","et":140.0},{"ci":"423112","et":110.0},{"ci":"422631","et":60.0},{"ci":"422958","et":10.0},{"ci":"7066","et":40.0},{"ci":"375144","et":70.0},{"ci":"424339","et":70.0},{"ci":"423208","et":40.0},{"ci":"325653","et":120.0},{"ci":"2960","et":80.0},{"ci":"401942","et":90.0},{"ci":"401875","et":80.0},{"ci":"401879","et":90.0},{"ci":"325654","et":120.0},{"ci":"424265","et":40.0},{"ci":"401876","et":80.0},{"ci":"422512","et":80.0},{"ci":"7071","et":130.0},{"ci":"423107","et":90.0},{"ci":"422674","et":150.0},{"ci":"423526","et":100.0},{"ci":"423257","et":80.0},{"ci":"422410","et":130.0},{"ci":"7069","et":130.0},{"ci":"401948","et":40.0},{"ci":"423478","et":90.0},{"ci":"423200","et":60.0},{"ci":"2948","et":15.0},{"ci":"423005","et":120.0},{"ci":"2959","et":80.0},{"ci":"401944","et":50.0},{"ci":"422629","et":15.0},{"ci":"401860","et":30.0},{"ci":"401958","et":90.0},{"ci":"423850","et":90.0},{"ci":"401947","et":40.0},{"ci":"424268","et":80.0},{"ci":"7080","et":80.0},{"ci":"422414","et":40.0},{"ci":"424552","et":10.0},{"ci":"401837","et":25.0},{"ci":"422050","et":170.0},{"ci":"422979","et":100.0},{"ci":"424649","et":80.0},{"ci":"422618","et":100.0},{"ci":"325649","et":60.0},{"ci":"424189","et":60.0},{"ci":"2937","et":60.0},{"ci":"423201","et":60.0},{"ci":"422661","et":190.0},{"ci":"424022","et":20.0},{"ci":"424203","et":60.0},{"ci":"424196","et":60.0},{"ci":"401834","et":25.0},{"ci":"424622","et":110.0},{"ci":"423207","et":60.0},{"ci":"359844","et":90.0},{"ci":"2954","et":120.0},{"ci":"401868","et":200.0},{"ci":"401956","et":90.0},{"ci":"424187","et":60.0},{"ci":"423849","et":100.0},{"ci":"401941","et":90.0},{"ci":"422415","et":40.0},{"ci":"375149","et":70.0},{"ci":"375145","et":70.0},{"ci":"423859","et":90.0},{"ci":"422504","et":100.0},{"ci":"375150","et":70.0},{"ci":"401949","et":110.0},{"ci":"422679","et":70.0},{"ci":"422412","et":130.0},{"ci":"422624","et":60.0},{"ci":"424342","et":70.0},{"ci":"424654","et":80.0},{"ci":"422630","et":15.0},{"ci":"422612","et":190.0},{"ci":"424331","et":70.0},{"ci":"422939","et":10.0},{"ci":"424650","et":110.0},{"ci":"424651","et":110.0},{"ci":"422620","et":15.0},{"ci":"423109","et":90.0},{"ci":"2933","et":60.0},{"ci":"401874","et":80.0},{"ci":"424200","et":100.0},{"ci":"310395","et":80.0},{"ci":"424627","et":110.0},{"ci":"401855","et":90.0},{"ci":"401863","et":30.0},{"ci":"401857","et":90.0},{"ci":"325659","et":10.0},{"ci":"422623","et":190.0},{"ci":"424332","et":70.0},{"ci":"423110","et":90.0},{"ci":"422621","et":190.0},{"ci":"423552","et":40.0},{"ci":"2940","et":20.0},{"ci":"422955","et":120.0},{"ci":"2949","et":15.0},{"ci":"2957","et":80.0},{"ci":"423003","et":120.0},{"ci":"424193","et":60.0},{"ci":"310400","et":80.0},{"ci":"422660","et":40.0},{"ci":"423259","et":80.0},{"ci":"423260","et":80.0},{"ci":"422192","et":100.0},{"ci":"2958","et":80.0},{"ci":"423258","et":80.0},{"ci":"401873","et":80.0},{"ci":"335167","et":80.0},{"ci":"7072","et":130.0},{"ci":"424343","et":80.0},{"ci":"401950","et":110.0},{"ci":"424334","et":70.0},{"ci":"422048","et":140.0},{"ci":"401937","et":80.0},{"ci":"401844","et":15.0},{"ci":"422964","et":120.0},{"ci":"2944","et":20.0},{"ci":"7070","et":130.0},{"ci":"422195","et":100.0},{"ci":"422495","et":170.0},{"ci":"423203","et":50.0},{"ci":"401954","et":70.0},{"ci":"423852","et":90.0},{"ci":"424345","et":70.0},{"ci":"401881","et":50.0},{"ci":"422615","et":190.0},{"ci":"423808","et":60.0},{"ci":"423477","et":90.0},{"ci":"423851","et":90.0},{"ci":"325647","et":60.0},{"ci":"424330","et":70.0},{"ci":"423844","et":140.0},{"ci":"422411","et":40.0},{"ci":"2946","et":15.0},{"ci":"359841","et":90.0},{"ci":"7075","et":130.0},{"ci":"423845","et":90.0},{"ci":"422047","et":170.0},{"ci":"422416","et":130.0},{"ci":"422627","et":15.0},{"ci":"2941","et":20.0},{"ci":"401955","et":70.0},{"ci":"310396","et":80.0},{"ci":"422666","et":200.0},{"ci":"423857","et":140.0},{"ci":"422667","et":190.0},{"ci":"423858","et":90.0},{"ci":"422628","et":100.0},{"ci":"422413","et":130.0},{"ci":"423843","et":140.0},{"ci":"422669","et":190.0},{"ci":"422418","et":130.0},{"ci":"2934","et":60.0},{"ci":"422194","et":100.0},{"ci":"422417","et":40.0},{"ci":"422190","et":100.0},{"ci":"422619","et":100.0},{"ci":"401869","et":80.0},{"ci":"7083","et":60.0},{"ci":"424258","et":120.0},{"ci":"401880","et":50.0},{"ci":"401845","et":15.0},{"ci":"401884","et":210.0},{"ci":"401835","et":25.0},{"ci":"423809","et":40.0},{"ci":"5033","et":15.0},{"ci":"335169","et":80.0},{"ci":"424185","et":100.0},{"ci":"423551","et":90.0},{"ci":"424202","et":60.0},{"ci":"401952","et":90.0},{"ci":"424015","et":80.0},{"ci":"2955","et":120.0},{"ci":"424624","et":110.0},{"ci":"375148","et":70.0},{"ci":"422616","et":15.0},{"ci":"401849","et":15.0},{"ci":"7079","et":80.0},{"ci":"325657","et":10.0},{"ci":"7078","et":80.0},{"ci":"325658","et":10.0},{"ci":"310394","et":80.0},{"ci":"7067","et":40.0},{"ci":"422617","et":15.0},{"ci":"401871","et":80.0},{"ci":"401877","et":90.0},{"ci":"10716","et":80.0},{"ci":"424344","et":80.0},{"ci":"423111","et":110.0},{"ci":"335170","et":80.0},{"ci":"424333","et":70.0},{"ci":"424703","et":10.0},{"ci":"401883","et":50.0},{"ci":"2953","et":120.0},{"ci":"401848","et":15.0},{"ci":"424195","et":60.0},{"ci":"424188","et":100.0},{"ci":"7085","et":25.0},{"ci":"401836","et":25.0},{"ci":"7082","et":60.0},{"ci":"359842","et":90.0},{"ci":"2942","et":20.0},{"ci":"401853","et":90.0},{"ci":"310398","et":80.0},{"ci":"422664","et":40.0},{"ci":"422665","et":200.0},{"ci":"424337","et":70.0},{"ci":"423847","et":90.0},{"ci":"401878","et":90.0},{"ci":"401866","et":30.0},{"ci":"2962","et":100.0},{"ci":"423479","et":90.0},{"ci":"401864","et":30.0},{"ci":"422957","et":10.0},{"ci":"401939","et":10.0},{"ci":"401858","et":90.0},{"ci":"422052","et":140.0},{"ci":"401840","et":25.0},{"ci":"422685","et":180.0},{"ci":"424192","et":60.0},{"ci":"401940","et":10.0},{"ci":"424198","et":100.0},{"ci":"401839","et":25.0},{"ci":"422663","et":200.0},{"ci":"401854","et":90.0},{"ci":"424555","et":10.0},{"ci":"401850","et":15.0},{"ci":"401851","et":15.0},{"ci":"401841","et":25.0},{"ci":"401856","et":90.0},{"ci":"2952","et":120.0},{"ci":"423209","et":40.0},{"ci":"401846","et":15.0},{"ci":"401938","et":80.0},{"ci":"422662","et":150.0},{"ci":"423035","et":80.0},{"ci":"422622","et":15.0},{"ci":"401862","et":30.0},{"ci":"401859","et":30.0},{"ci":"401852","et":90.0},{"ci":"424621","et":110.0},{"ci":"422675","et":70.0},{"ci":"423568","et":15.0},{"ci":"424204","et":60.0},{"ci":"401847","et":15.0},{"ci":"423106","et":90.0},{"ci":"7077","et":80.0},{"ci":"401842","et":25.0},{"ci":"423205","et":50.0},{"ci":"359843","et":90.0},{"ci":"422613","et":190.0},{"ci":"7074","et":130.0},{"ci":"424190","et":100.0},{"ci":"422625","et":15.0},{"ci":"424199","et":100.0},{"ci":"424267","et":30.0},{"ci":"2963","et":100.0},{"ci":"2936","et":60.0}]