[{"cn":"dav0311","pi":"423951","ui":"8268274","ci":"424181","ri":"424182","ti":"424186","t":12073,"r":12003,"q":1.36,"p":1.0,"mot":"L","mo":10},{"cn":"dav0311","pi":"423951","ui":"9212043","ci":"325645","ri":"325646","ti":"325648","t":117058,"r":114053,"q":4.89,"p":1.0,"mot":"L","mo":100},{"cn":"АО «BLESK»","pi":"423951","ui":"7385509","ci":"303253","ri":"303254","ti":"303261","t":11778,"r":11778,"q":4.64,"p":35.0,"mot":"U","mo":0},{"cn":"Николаев  А. Ltd.","pi":"423951","ui":"10972103","ci":"2931","ri":"2932","ti":"424027","t":3600,"r":3600,"q":1.0,"p":36.0,"mot":"U","mo":0},{"cn":"Umnitsa Ltd.","pi":"423951","ui":"10876141","ci":"424181","ri":"424182","ti":"424194","t":90472,"r":86422,"q":20.03,"p":39.99,"mot":"U","mo":0},{"cn":"MS","pi":"423951","ui":"9220020","ci":"424181","ri":"424182","ti":"424186","t":26501824,"r":26322164,"q":17.37,"p":40.0,"mot":"U","mo":0},{"cn":"АО «BLESK»","pi":"423951","ui":"7261057","ci":"2931","ri":"2945","ti":"2948","t":1500,"r":1500,"q":2.75,"p":50.0,"mot":"U","mo":0},{"cn":"Constantin","pi":"423951","ui":"10790402","ci":"424181","ri":"424182","ti":"424196","t":2553508,"r":2553508,"q":15.79,"p":52.0,"mot":"U","mo":0},{"cn":"T_IGRIK Инвест","pi":"423951","ui":"9910972","ci":"424181","ri":"424182","ti":"424186","t":496212,"r":496212,"q":18.21,"p":55.0,"mot":"U","mo":0},{"cn":"Galina_gf Ltd.","pi":"423951","ui":"10727116","ci":"424181","ri":"424182","ti":"424196","t":1591386,"r":1591386,"q":14.05,"p":60.0,"mot":"L","mo":50000},{"cn":"MS","pi":"423951","ui":"9219999","ci":"2931","ri":"2961","ti":"423526","t":47633,"r":7633,"q":10.8,"p":77.0,"mot":"U","mo":0},{"cn":"Dkozitskiy1 Ltd.","pi":"423951","ui":"10963464","ci":"3010","ri":"3023","ti":"3025","t":77804,"r":77804,"q":9.49,"p":80.0,"mot":"U","mo":0},{"cn":"Свой путь","pi":"423951","ui":"9539643","ci":"3010","ri":"3023","ti":"3025","t":2686962,"r":2594943,"q":9.47,"p":85.0,"mot":"U","mo":0},{"cn":"RALF Inc.","pi":"423951","ui":"727443","ci":"2931","ri":"2932","ti":"2938","t":173197,"r":172697,"q":14.99,"p":86.0,"mot":"U","mo":0},{"cn":"Amtriz Co","pi":"423951","ui":"10014046","ci":"422983","ri":"422984","ti":"422985","t":175122,"r":175122,"q":3.54,"p":90.0,"mot":"U","mo":0},{"cn":"Симонова Финанс","pi":"423951","ui":"6959774","ci":"423554","ri":"423555","ti":"423560","t":63494,"r":63494,"q":7.29,"p":98.36,"mot":"U","mo":0},{"cn":"BORYSPIL UA","pi":"423951","ui":"8182210","ci":"325645","ri":"325646","ti":"422513","t":1935901,"r":1570809,"q":18.76,"p":99.99,"mot":"L","mo":10000},{"cn":"Amtriz Co","pi":"423951","ui":"10996557","ci":"422362","ri":"422363","ti":"422366","t":21048,"r":20748,"q":24.13,"p":100.0,"mot":"U","mo":0},{"cn":"Vsen Ltd.","pi":"423951","ui":"9678928","ci":"424181","ri":"424184","ti":"424202","t":32312,"r":32292,"q":5.24,"p":100.0,"mot":"U","mo":0},{"cn":"J.k.21st92 Ltd.","pi":"423951","ui":"7441929","ci":"422607","ri":"422610","ti":"424048","t":80375,"r":80375,"q":4.81,"p":115.28,"mot":"U","mo":0},{"cn":"J.k.21st92 Ltd.","pi":"423951","ui":"5748182","ci":"15734","ri":"15735","ti":"15739","t":37001,"r":37001,"q":6.83,"p":118.54,"mot":"U","mo":0},{"cn":"Оптовира","pi":"423951","ui":"10887608","ci":"2931","ri":"2945","ti":"2948","t":3374015,"r":252345,"q":46.9,"p":119.0,"mot":"U","mo":0},{"cn":"Симонова Финанс","pi":"423951","ui":"7443484","ci":"310392","ri":"310393","ti":"424004","t":97308,"r":97308,"q":3.16,"p":121.85,"mot":"U","mo":0},{"cn":"Симонова Финанс","pi":"423951","ui":"6010698","ci":"303829","ri":"303830","ti":"303832","t":77740,"r":77740,"q":8.79,"p":125.35,"mot":"U","mo":0},{"cn":"Симонова Финанс","pi":"423951","ui":"5925587","ci":"2931","ri":"2950","ti":"2955","t":96279,"r":96279,"q":4.91,"p":125.35,"mot":"U","mo":0},{"cn":"J.k.21st92 Ltd.","pi":"423951","ui":"6705278","ci":"325645","ri":"325646","ti":"325647","t":37006,"r":37006,"q":5.19,"p":125.37,"mot":"U","mo":0},{"cn":"Симонова Финанс","pi":"423951","ui":"7026161","ci":"15906","ri":"3030","ti":"422528","t":249213,"r":249213,"q":5.6,"p":125.38,"mot":"U","mo":0},{"cn":"Симонова Финанс","pi":"423951","ui":"7514208","ci":"2931","ri":"2950","ti":"423005","t":51929,"r":51929,"q":7.19,"p":125.65,"mot":"U","mo":0},{"cn":"Симонова Финанс","pi":"423951","ui":"6934853","ci":"325645","ri":"325646","ti":"422037","t":45870,"r":45870,"q":6.69,"p":125.82,"mot":"U","mo":0},{"cn":"АО «BLESK»","pi":"423951","ui":"7100178","ci":"325645","ri":"325646","ti":"422037","t":27113418,"r":22542782,"q":29.11,"p":130.0,"mot":"U","mo":0},{"cn":"Sannitta Инвест","pi":"423951","ui":"7333921","ci":"7060","ri":"7062","ti":"7070","t":113653821,"r":112516421,"q":20.21,"p":135.0,"mot":"U","mo":0},{"cn":"Симонова Финанс","pi":"423951","ui":"6589895","ci":"15734","ri":"15735","ti":"15736","t":127684,"r":127684,"q":5.58,"p":135.24,"mot":"U","mo":0},{"cn":"Симонова Финанс","pi":"423951","ui":"5959195","ci":"422607","ri":"422611","ti":"422624","t":21000,"r":21000,"q":4.45,"p":135.62,"mot":"U","mo":0},{"cn":"Liberty Inc.","pi":"423951","ui":"8050765","ci":"424181","ri":"424182","ti":"424192","t":55251,"r":55251,"q":3.69,"p":138.78,"mot":"U","mo":0},{"cn":"Constantin","pi":"423951","ui":"10824732","ci":"424181","ri":"424184","ti":"424201","t":22600,"r":22100,"q":15.79,"p":140.0,"mot":"U","mo":0},{"cn":"Симонова Финанс","pi":"423951","ui":"6434449","ci":"7060","ri":"7061","ti":"7067","t":146501,"r":146501,"q":5.89,"p":145.28,"mot":"U","mo":0},{"cn":"J.k.21st92 Ltd.","pi":"423951","ui":"6232875","ci":"423103","ri":"423104","ti":"423109","t":136901,"r":136901,"q":7.92,"p":145.38,"mot":"U","mo":0},{"cn":"Симонова Финанс","pi":"423951","ui":"7080096","ci":"423554","ri":"423555","ti":"423558","t":51400,"r":51400,"q":6.98,"p":145.72,"mot":"U","mo":0},{"cn":"Агро-Био-Фарм","pi":"423951","ui":"7482049","ci":"310392","ri":"310393","ti":"310398","t":23197,"r":3197,"q":11.74,"p":150.0,"mot":"U","mo":0},{"cn":"Toppers и сыновья","pi":"423951","ui":"7449754","ci":"325645","ri":"325646","ti":"424049","t":112802551,"r":112799781,"q":15.14,"p":150.0,"mot":"U","mo":0},{"cn":"Yullium Ltd.","pi":"423951","ui":"10760599","ci":"2931","ri":"2939","ti":"2940","t":607874,"r":107874,"q":16.02,"p":155.0,"mot":"U","mo":0},{"cn":"J.k.21st92 Ltd.","pi":"423951","ui":"5644586","ci":"301309","ri":"301310","ti":"301312","t":10696,"r":10696,"q":5.17,"p":157.54,"mot":"U","mo":0},{"cn":"Симонова Финанс","pi":"423951","ui":"6478371","ci":"422607","ri":"422609","ti":"422626","t":39188,"r":39188,"q":6.72,"p":165.35,"mot":"U","mo":0},{"cn":"Симонова Финанс","pi":"423951","ui":"7486667","ci":"310392","ri":"310393","ti":"422512","t":161610,"r":161610,"q":4.14,"p":165.58,"mot":"U","mo":0},{"cn":"J.k.21st92 Ltd.","pi":"423951","ui":"6831444","ci":"2931","ri":"2961","ti":"2964","t":24000,"r":24000,"q":12.04,"p":173.65,"mot":"U","mo":0},{"cn":"J.k.21st92 Ltd.","pi":"423951","ui":"5815331","ci":"303253","ri":"303254","ti":"303258","t":276313,"r":276313,"q":8.82,"p":175.45,"mot":"U","mo":0},{"cn":"Симонова Финанс","pi":"423951","ui":"6755880","ci":"423195","ri":"423197","ti":"423205","t":6010,"r":6010,"q":9.25,"p":175.78,"mot":"U","mo":0},{"cn":"Симонова Финанс","pi":"423951","ui":"7449529","ci":"325650","ri":"325651","ti":"424062","t":200000,"r":200000,"q":10.6,"p":185.26,"mot":"U","mo":0},{"cn":"Evseev.n.a Ltd.","pi":"423951","ui":"10002033","ci":"303253","ri":"303254","ti":"303259","t":3107767,"r":3097767,"q":18.32,"p":195.0,"mot":"U","mo":0},{"cn":"Ronirus  GR","pi":"423951","ui":"9717210","ci":"15905","ri":"3042","ti":"424293","t":2199,"r":2199,"q":3.41,"p":200.0,"mot":"U","mo":0},{"cn":"BORYSPIL UA","pi":"423951","ui":"9008353","ci":"2931","ri":"2961","ti":"2963","t":240553264,"r":239847664,"q":14.56,"p":200.0,"mot":"U","mo":0},{"cn":"Огни Баку","pi":"423951","ui":"3623853","ci":"2931","ri":"2932","ti":"2936","t":2000000,"r":2000000,"q":14.96,"p":200.0,"mot":"U","mo":0},{"cn":"BORYSPIL UA","pi":"423951","ui":"8811127","ci":"2931","ri":"2932","ti":"2933","t":36692,"r":36182,"q":14.42,"p":209.99,"mot":"L","mo":500},{"cn":"Inplayer Финанс","pi":"423951","ui":"6313844","ci":"2931","ri":"2961","ti":"366263","t":1706,"r":1706,"q":3.77,"p":215.38,"mot":"U","mo":0},{"cn":"АО «BLESK»","pi":"423951","ui":"7297685","ci":"325645","ri":"325646","ti":"422037","t":12776101,"r":12042691,"q":28.6,"p":220.0,"mot":"U","mo":0},{"cn":"Megacorp inc","pi":"423951","ui":"9878423","ci":"423554","ri":"423555","ti":"423559","t":1285000,"r":1285000,"q":15.3,"p":220.0,"mot":"U","mo":0},{"cn":"Симонова Финанс","pi":"423951","ui":"5925582","ci":"2931","ri":"2950","ti":"2955","t":48781,"r":48781,"q":4.3,"p":225.86,"mot":"U","mo":0},{"cn":"J.k.21st92 Ltd.","pi":"423951","ui":"5810596","ci":"3054","ri":"3055","ti":"3057","t":2501,"r":2501,"q":2.17,"p":247.35,"mot":"U","mo":0},{"cn":"Toppers и сыновья","pi":"423951","ui":"8275520","ci":"422607","ri":"422611","ti":"422631","t":3693645,"r":3693295,"q":17.85,"p":250.0,"mot":"U","mo":0},{"cn":"Симонова Финанс","pi":"423951","ui":"5648190","ci":"15734","ri":"15735","ti":"16322","t":192000,"r":192000,"q":2.25,"p":250.38,"mot":"U","mo":0},{"cn":"Симонова Финанс","pi":"423951","ui":"5607663","ci":"15904","ri":"15916","ti":"373539","t":20000,"r":20000,"q":7.07,"p":254.86,"mot":"U","mo":0},{"cn":"J.k.21st92 Ltd.","pi":"423951","ui":"6404868","ci":"423103","ri":"423105","ti":"423113","t":26360,"r":26360,"q":5.11,"p":258.64,"mot":"U","mo":0},{"cn":"Симонова Финанс","pi":"423951","ui":"6705337","ci":"15734","ri":"15735","ti":"16322","t":42500,"r":42500,"q":9.09,"p":275.34,"mot":"U","mo":0},{"cn":"J.k.21st92 Ltd.","pi":"423951","ui":"6294787","ci":"310392","ri":"310393","ti":"310400","t":344280,"r":344280,"q":16.42,"p":276.63,"mot":"U","mo":0},{"cn":"Inplayer Финанс","pi":"423951","ui":"5683883","ci":"2931","ri":"2945","ti":"366652","t":25178,"r":25178,"q":5.2,"p":285.35,"mot":"U","mo":0},{"cn":"barlat","pi":"423951","ui":"8931524","ci":"15906","ri":"3030","ti":"3035","t":8498151,"r":8379051,"q":29.19,"p":287.84,"mot":"U","mo":0},{"cn":"J.k.21st92 Ltd.","pi":"423951","ui":"5734333","ci":"310392","ri":"310393","ti":"310400","t":390015,"r":390015,"q":13.86,"p":295.85,"mot":"U","mo":0},{"cn":"kasap Финанс","pi":"423951","ui":"7275701","ci":"423103","ri":"423105","ti":"423112","t":1905383,"r":1905383,"q":13.61,"p":300.0,"mot":"U","mo":0},{"cn":"J.k.21st92 Ltd.","pi":"423951","ui":"7461355","ci":"310392","ri":"310393","ti":"310398","t":33141,"r":33141,"q":5.88,"p":315.76,"mot":"U","mo":0},{"cn":"Симонова Финанс","pi":"423951","ui":"6583209","ci":"303253","ri":"303254","ti":"422076","t":592200,"r":592200,"q":10.53,"p":315.85,"mot":"U","mo":0},{"cn":"J.k.21st92 Ltd.","pi":"423951","ui":"6394589","ci":"325645","ri":"325646","ti":"325649","t":5288,"r":5288,"q":4.45,"p":318.25,"mot":"U","mo":0},{"cn":"Симонова Финанс","pi":"423951","ui":"6385703","ci":"422043","ri":"422045","ti":"422515","t":93000,"r":93000,"q":8.71,"p":325.65,"mot":"U","mo":0},{"cn":"J.k.21st92 Ltd.","pi":"423951","ui":"6679241","ci":"423581","ri":"423582","ti":"423584","t":99497,"r":99497,"q":8.98,"p":325.84,"mot":"U","mo":0},{"cn":"Inplayer Финанс","pi":"423951","ui":"5614726","ci":"310392","ri":"310393","ti":"310399","t":35166,"r":35166,"q":5.5,"p":385.62,"mot":"U","mo":0},{"cn":"J.k.21st92 Ltd.","pi":"423951","ui":"7140130","ci":"375142","ri":"375143","ti":"375147","t":136526,"r":136526,"q":14.65,"p":387.93,"mot":"U","mo":0},{"cn":"Dedinvest","pi":"423951","ui":"7868675","ci":"424181","ri":"424184","ti":"424203","t":131004,"r":131004,"q":10.05,"p":400.0,"mot":"U","mo":0},{"cn":"Ax@Ox","pi":"423951","ui":"9332644","ci":"424181","ri":"424183","ti":"424188","t":60648,"r":60648,"q":15.49,"p":400.0,"mot":"U","mo":0},{"cn":"Toppers и сыновья","pi":"423951","ui":"7400434","ci":"325645","ri":"325646","ti":"424049","t":254840,"r":253840,"q":21.11,"p":400.0,"mot":"U","mo":0},{"cn":"Симонова Финанс","pi":"423951","ui":"6626461","ci":"423103","ri":"423105","ti":"423111","t":138998,"r":138998,"q":2.81,"p":451.26,"mot":"U","mo":0},{"cn":"VIRTO","pi":"423951","ui":"10796140","ci":"2931","ri":"331858","ti":"331873","t":1085891,"r":1085891,"q":11.08,"p":455.0,"mot":"U","mo":0},{"cn":"Симонова Финанс","pi":"423951","ui":"6596444","ci":"15905","ri":"3042","ti":"422977","t":9370,"r":9370,"q":2.96,"p":455.26,"mot":"U","mo":0},{"cn":"VIRTO","pi":"423951","ui":"10788627","ci":"2931","ri":"2932","ti":"422040","t":306504,"r":295421,"q":8.31,"p":470.0,"mot":"U","mo":0},{"cn":"J.k.21st92 Ltd.","pi":"423951","ui":"6658559","ci":"15905","ri":"3042","ti":"3049","t":178001,"r":178001,"q":4.48,"p":475.24,"mot":"U","mo":0},{"cn":"OsinComp","pi":"423951","ui":"7511352","ci":"325650","ri":"325651","ti":"325653","t":5364,"r":5364,"q":7.42,"p":510.0,"mot":"U","mo":0},{"cn":"Симонова Финанс","pi":"423951","ui":"6405531","ci":"325655","ri":"325656","ti":"325659","t":4654,"r":4654,"q":2.45,"p":515.63,"mot":"U","mo":0},{"cn":"Симонова Финанс","pi":"423951","ui":"5765722","ci":"422607","ri":"422609","ti":"422632","t":2598,"r":2598,"q":9.92,"p":524.36,"mot":"U","mo":0},{"cn":"Amtriz Co","pi":"423951","ui":"6476458","ci":"422607","ri":"422608","ti":"422617","t":11805241,"r":11805241,"q":11.92,"p":800.0,"mot":"U","mo":0},{"cn":"LTD Orion","pi":"423951","ui":"8788719","ci":"325645","ri":"325646","ti":"325648","t":300001,"r":300001,"q":21.5,"p":800.0,"mot":"U","mo":0},{"cn":"IvanM1980 и компания","pi":"423951","ui":"8727762","ci":"325645","ri":"325646","ti":"325648","t":319203744,"r":318769673,"q":35.08,"p":800.0,"mot":"U","mo":0},{"cn":"Симонова Финанс","pi":"423951","ui":"7138313","ci":"3010","ri":"3018","ti":"3020","t":82584,"r":82584,"q":9.08,"p":956.37,"mot":"U","mo":0},{"cn":"Vsen Ltd.","pi":"423951","ui":"8830019","ci":"424181","ri":"424183","ti":"424190","t":39646,"r":39646,"q":4.95,"p":1500.0,"mot":"U","mo":0},{"cn":"pavel32024 и сыновья","pi":"423951","ui":"7515497","ci":"422607","ri":"422608","ti":"422625","t":1120748,"r":1120748,"q":1.01,"p":1700.0,"mot":"U","mo":0},{"cn":"Myxa Inc","pi":"423951","ui":"7337575","ci":"325645","ri":"325646","ti":"325648","t":9005085,"r":8905085,"q":14.77,"p":1889.67,"mot":"U","mo":0},{"cn":"АО «ПОГАНКА»","pi":"423951","ui":"5968672","ci":"310392","ri":"310393","ti":"310400","t":10262355,"r":8308739,"q":60.01,"p":2000.0,"mot":"L","mo":100000},{"cn":"Megacorp inc","pi":"423951","ui":"9571490","ci":"303253","ri":"303254","ti":"424564","t":332500,"r":332500,"q":32.51,"p":2000.0,"mot":"U","mo":0},{"cn":"BEREZOVES Финанс","pi":"423951","ui":"9010919","ci":"325645","ri":"325646","ti":"422037","t":72894,"r":72894,"q":40.2,"p":2999.0,"mot":"U","mo":0},{"cn":"ДВ Торг","pi":"423951","ui":"7315274","ci":"325650","ri":"325651","ti":"422940","t":172000,"r":74000,"q":59.35,"p":12500.0,"mot":"U","mo":0}]