[{"cn":"HyperStark Industry","pi":"370072","ui":"5690047","ci":"401799","ri":"401826","ti":"401942","t":30659,"r":24647,"q":14.68,"p":25000.0,"mot":"U","mo":0},{"cn":"HyperStark Industry","pi":"370072","ui":"5102026","ci":"401791","ri":"401806","ti":"401859","t":56721,"r":54139,"q":15.74,"p":34000.0,"mot":"U","mo":0},{"cn":"Dodge Diamond Mantis","pi":"370072","ui":"3188356","ci":"401801","ri":"401829","ti":"401949","t":7446,"r":7444,"q":12.53,"p":34333.33,"mot":"L","mo":1},{"cn":"Glukes Ltd.","pi":"370072","ui":"3848510","ci":"325655","ri":"325656","ti":"325657","t":1164656,"r":1162104,"q":32.75,"p":40000.0,"mot":"U","mo":0},{"cn":"Glukes Ltd.","pi":"370072","ui":"5271497","ci":"401798","ri":"401825","ti":"401940","t":901062,"r":873416,"q":17.75,"p":50000.0,"mot":"U","mo":0}]